<?xml version="1.0"?>
<rec type="areas">
 <no/><!-- Land Bridge -->
 <no/><!-- English Channel Coast -->
 <no/><!-- Passable -->
 <v2 x="230.16444" y="86.26195"/>
 <v2 x="311.02142" y="212.93451"/>
 <u2>91</u2><!-- Adjoning Passable Areas ID -->
 <rec type="faces">
  <u4_ary>
   27617 <!-- 232.65428 210.37479-->
   33008 <!-- 230.48358 210.00018-->
   35124 <!-- 230.16444 210.56436-->
   27617 <!-- 232.65428 210.37479-->
   35124 <!-- 230.16444 210.56436-->
   36337 <!-- 230.51561 211.48085-->
   27617 <!-- 232.65428 210.37479-->
   27923 <!-- 232.79333 210.00018-->
   33008 <!-- 230.48358 210.00018-->
   27617 <!-- 232.65428 210.37479-->
   36337 <!-- 230.51561 211.48085-->
   28312 <!-- 231.18513 212.0182-->
   27617 <!-- 232.65428 210.37479-->
   28312 <!-- 231.18513 212.0182-->
   35297 <!-- 232.01599 212.0182-->
   31937 <!-- 232.55858 211.7653-->
   27617 <!-- 232.65428 210.37479-->
   35297 <!-- 232.01599 212.0182-->
   28312 <!-- 231.18513 212.0182-->
   35542 <!-- 231.44139 212.77669-->
   35297 <!-- 232.01599 212.0182-->
   35542 <!-- 231.44139 212.77669-->
   31721 <!-- 231.79218 212.93451-->
   35297 <!-- 232.01599 212.0182-->
   22537 <!-- 231.88788 209.04738-->
   33008 <!-- 230.48358 210.00018-->
   27923 <!-- 232.79333 210.00018-->
   22537 <!-- 231.88788 209.04738-->
   27923 <!-- 232.79333 210.00018-->
   27066 <!-- 232.8781 209.77411-->
   24069 <!-- 232.39879 207.62509-->
   22537 <!-- 231.88788 209.04738-->
   28320 <!-- 233.26054 209.3632-->
   22537 <!-- 231.88788 209.04738-->
   27066 <!-- 232.8781 209.77411-->
   28320 <!-- 233.26054 209.3632-->
   30187 <!-- 233.96288 207.90956-->
   17385 <!-- 232.36676 205.94992-->
   24069 <!-- 232.39879 207.62509-->
   30187 <!-- 233.96288 207.90956-->
   27896 <!-- 234.99959 207.30908-->
   17385 <!-- 232.36676 205.94992-->
   27896 <!-- 234.99959 207.30908-->
   16233 <!-- 232.94177 204.99989-->
   17385 <!-- 232.36676 205.94992-->
   27896 <!-- 234.99959 207.30908-->
   11691 <!-- 234.99998 205.00009-->
   16233 <!-- 232.94177 204.99989-->
   30187 <!-- 233.96288 207.90956-->
   24069 <!-- 232.39879 207.62509-->
   23803 <!-- 233.48438 208.98405-->
   30187 <!-- 233.96288 207.90956-->
   23803 <!-- 233.48438 208.98405-->
   27218 <!-- 233.83513 208.88937-->
   24069 <!-- 232.39879 207.62509-->
   28320 <!-- 233.26054 209.3632-->
   23803 <!-- 233.48438 208.98405-->
   11691 <!-- 234.99998 205.00009-->
   27896 <!-- 234.99959 207.30908-->
   12269 <!-- 235.62262 206.4557-->
   40598 <!-- 236.22928 205.00009-->
   11691 <!-- 234.99998 205.00009-->
   12269 <!-- 235.62262 206.4557-->
   40598 <!-- 236.22928 205.00009-->
   12269 <!-- 235.62262 206.4557-->
   37938 <!-- 236.22928 206.20282-->
   15504 <!-- 234.99959 202.34686-->
   11691 <!-- 234.99998 205.00009-->
   31672 <!-- 236.2617 203.29512-->
   11691 <!-- 234.99998 205.00009-->
   40598 <!-- 236.22928 205.00009-->
   31672 <!-- 236.2617 203.29512-->
   15504 <!-- 234.99959 202.34686-->
   31672 <!-- 236.2617 203.29512-->
   31021 <!-- 236.74023 203.13731-->
   15504 <!-- 234.99959 202.34686-->
   31021 <!-- 236.74023 203.13731-->
   34330 <!-- 236.99567 202.53664-->
   15504 <!-- 234.99959 202.34686-->
   34330 <!-- 236.99567 202.53664-->
   30939 <!-- 237.50586 202.31509-->
   50317 <!-- 236.90038 200.0-->
   15504 <!-- 234.99959 202.34686-->
   30706 <!-- 237.85742 201.77834-->
   15504 <!-- 234.99959 202.34686-->
   30939 <!-- 237.50586 202.31509-->
   30706 <!-- 237.85742 201.77834-->
   50317 <!-- 236.90038 200.0-->
   30706 <!-- 237.85742 201.77834-->
   50533 <!-- 238.39998 201.55701-->
   50317 <!-- 236.90038 200.0-->
   50533 <!-- 238.39998 201.55701-->
   41391 <!-- 238.84685 200.89302-->
   17374 <!-- 233.73981 204.55939-->
   16233 <!-- 232.94177 204.99989-->
   11691 <!-- 234.99998 205.00009-->
   17374 <!-- 233.73981 204.55939-->
   16912 <!-- 234.4742 203.10536-->
   14537 <!-- 233.67577 203.32687-->
   17374 <!-- 233.73981 204.55939-->
   11691 <!-- 234.99998 205.00009-->
   16912 <!-- 234.4742 203.10536-->
   11691 <!-- 234.99998 205.00009-->
   15504 <!-- 234.99959 202.34686-->
   16912 <!-- 234.4742 203.10536-->
   44343 <!-- 238.62381 198.80714-->
   50317 <!-- 236.90038 200.0-->
   44935 <!-- 239.51717 200.0-->
   44935 <!-- 239.51717 200.0-->
   50317 <!-- 236.90038 200.0-->
   41391 <!-- 238.84685 200.89302-->
   44935 <!-- 239.51717 200.0-->
   41391 <!-- 238.84685 200.89302-->
   41227 <!-- 239.2941 200.70363-->
   46572 <!-- 239.03865 198.11197-->
   44343 <!-- 238.62381 198.80714-->
   44935 <!-- 239.51717 200.0-->
   41722 <!-- 239.99957 199.43918-->
   46572 <!-- 239.03865 198.11197-->
   44935 <!-- 239.51717 200.0-->
   41722 <!-- 239.99957 199.43918-->
   46496 <!-- 239.99997 197.28996-->
   46572 <!-- 239.03865 198.11197-->
   46496 <!-- 239.99997 197.28996-->
   41722 <!-- 239.99957 199.43918-->
   50251 <!-- 240.63435 198.83867-->
   58380 <!-- 240.76208 196.6581-->
   46496 <!-- 239.99997 197.28996-->
   31419 <!-- 241.56013 198.39622-->
   46496 <!-- 239.99997 197.28996-->
   50251 <!-- 240.63435 198.83867-->
   31419 <!-- 241.56013 198.39622-->
   55505 <!-- 239.99997 194.99989-->
   980 <!-- 239.99957 196.31015-->
   889 <!-- 240.69841 195.80475-->
   7056 <!-- 244.99959 195.00009-->
   55505 <!-- 239.99997 194.99989-->
   889 <!-- 240.69841 195.80475-->
   7056 <!-- 244.99959 195.00009-->
   889 <!-- 240.69841 195.80475-->
   58380 <!-- 240.76208 196.6581-->
   7056 <!-- 244.99959 195.00009-->
   58380 <!-- 240.76208 196.6581-->
   32210 <!-- 243.28355 197.29016-->
   7056 <!-- 244.99959 195.00009-->
   32210 <!-- 243.28355 197.29016-->
   32623 <!-- 243.55446 197.38504-->
   7056 <!-- 244.99959 195.00009-->
   32623 <!-- 243.55446 197.38504-->
   35724 <!-- 244.12906 198.26978-->
   35793 <!-- 244.72751 198.90181-->
   7056 <!-- 244.99959 195.00009-->
   35724 <!-- 244.12906 198.26978-->
   58380 <!-- 240.76208 196.6581-->
   31419 <!-- 241.56013 198.39622-->
   33743 <!-- 241.94333 197.85887-->
   58380 <!-- 240.76208 196.6581-->
   33743 <!-- 241.94333 197.85887-->
   31717 <!-- 242.83708 197.6693-->
   58380 <!-- 240.76208 196.6581-->
   31717 <!-- 242.83708 197.6693-->
   32210 <!-- 243.28355 197.29016-->
   32623 <!-- 243.55446 197.38504-->
   36617 <!-- 243.74625 198.11176-->
   35724 <!-- 244.12906 198.26978-->
   35793 <!-- 244.72751 198.90181-->
   35724 <!-- 244.12906 198.26978-->
   36783 <!-- 244.22516 198.80693-->
   32983 <!-- 245.08688 200.0-->
   30921 <!-- 244.72751 201.24078-->
   30067 <!-- 246.65955 200.45074-->
   29458 <!-- 246.59589 200.00018-->
   32983 <!-- 245.08688 200.0-->
   30067 <!-- 246.65955 200.45074-->
   32983 <!-- 245.08688 200.0-->
   29458 <!-- 246.59589 200.00018-->
   29938 <!-- 246.72362 199.37604-->
   31238 <!-- 244.99078 199.47093-->
   32983 <!-- 245.08688 200.0-->
   29938 <!-- 246.72362 199.37604-->
   30921 <!-- 244.72751 201.24078-->
   52250 <!-- 244.72789 202.22061-->
   47397 <!-- 245.37437 202.37842-->
   30921 <!-- 244.72751 201.24078-->
   26738 <!-- 247.1701 200.577-->
   30067 <!-- 246.65955 200.45074-->
   30921 <!-- 244.72751 201.24078-->
   47397 <!-- 245.37437 202.37842-->
   26738 <!-- 247.1701 200.577-->
   47397 <!-- 245.37437 202.37842-->
   9632 <!-- 247.42557 201.84126-->
   26738 <!-- 247.1701 200.577-->
   47397 <!-- 245.37437 202.37842-->
   10702 <!-- 248.03223 202.28374-->
   9632 <!-- 247.42557 201.84126-->
   7056 <!-- 244.99959 195.00009-->
   35793 <!-- 244.72751 198.90181-->
   31238 <!-- 244.99078 199.47093-->
   7056 <!-- 244.99959 195.00009-->
   31238 <!-- 244.99078 199.47093-->
   29938 <!-- 246.72362 199.37604-->
   7056 <!-- 244.99959 195.00009-->
   29938 <!-- 246.72362 199.37604-->
   20723 <!-- 247.13846 199.18607-->
   17650 <!-- 249.99995 195.00009-->
   7056 <!-- 244.99959 195.00009-->
   20723 <!-- 247.13846 199.18607-->
   17650 <!-- 249.99995 195.00009-->
   20723 <!-- 247.13846 199.18607-->
   27189 <!-- 248.15993 199.53424-->
   17650 <!-- 249.99995 195.00009-->
   27189 <!-- 248.15993 199.53424-->
   23753 <!-- 249.19281 199.72382-->
   20328 <!-- 249.99995 199.50249-->
   17650 <!-- 249.99995 195.00009-->
   23753 <!-- 249.19281 199.72382-->
   17650 <!-- 249.99995 195.00009-->
   20328 <!-- 249.99995 199.50249-->
   10784 <!-- 251.01169 198.76747-->
   17650 <!-- 249.99995 195.00009-->
   10784 <!-- 251.01169 198.76747-->
   38234 <!-- 252.50192 196.62221-->
   17650 <!-- 249.99995 195.00009-->
   38234 <!-- 252.50192 196.62221-->
   36988 <!-- 252.63669 195.90692-->
   31350 <!-- 253.67537 195.00009-->
   17650 <!-- 249.99995 195.00009-->
   36988 <!-- 252.63669 195.90692-->
   28745 <!-- 249.99995 189.99998-->
   17650 <!-- 249.99995 195.00009-->
   37230 <!-- 254.39723 192.91223-->
   17650 <!-- 249.99995 195.00009-->
   31350 <!-- 253.67537 195.00009-->
   34921 <!-- 254.35229 193.98495-->
   17650 <!-- 249.99995 195.00009-->
   34921 <!-- 254.35229 193.98495-->
   37230 <!-- 254.39723 192.91223-->
   18632 <!-- 254.99959 190.0002-->
   28745 <!-- 249.99995 189.99998-->
   37230 <!-- 254.39723 192.91223-->
   34300 <!-- 254.99959 192.15257-->
   18632 <!-- 254.99959 190.0002-->
   37230 <!-- 254.39723 192.91223-->
   7678 <!-- 254.99997 185.00031-->
   18632 <!-- 254.99959 190.0002-->
   56224 <!-- 257.37732 190.0002-->
   18632 <!-- 254.99959 190.0002-->
   34300 <!-- 254.99959 192.15257-->
   57391 <!-- 256.33865 191.21376-->
   57391 <!-- 256.33865 191.21376-->
   56224 <!-- 257.37732 190.0002-->
   18632 <!-- 254.99959 190.0002-->
   5985 <!-- 259.5437 185.6714-->
   7678 <!-- 254.99997 185.00031-->
   56224 <!-- 257.37732 190.0002-->
   5985 <!-- 259.5437 185.6714-->
   3100 <!-- 259.99957 185.00011-->
   7678 <!-- 254.99997 185.00031-->
   5985 <!-- 259.5437 185.6714-->
   4521 <!-- 259.99957 185.51636-->
   3100 <!-- 259.99957 185.00011-->
   3100 <!-- 259.99957 185.00011-->
   4521 <!-- 259.99957 185.51636-->
   23738 <!-- 260.98865 185.17982-->
   23738 <!-- 260.98865 185.17982-->
   21675 <!-- 261.07925 185.00031-->
   3100 <!-- 259.99957 185.00011-->
   3100 <!-- 259.99957 185.00011-->
   21675 <!-- 261.07925 185.00031-->
   13185 <!-- 260.5824 183.92816-->
   21675 <!-- 261.07925 185.00031-->
   15339 <!-- 261.34998 184.46434-->
   13185 <!-- 260.5824 183.92816-->
   14180 <!-- 259.99997 180.00002-->
   3100 <!-- 259.99957 185.00011-->
   13185 <!-- 260.5824 183.92816-->
   14180 <!-- 259.99997 180.00002-->
   13185 <!-- 260.5824 183.92816-->
   18253 <!-- 260.94333 182.94479-->
   14180 <!-- 259.99997 180.00002-->
   18253 <!-- 260.94333 182.94479-->
   16550 <!-- 262.02692 182.7661-->
   14180 <!-- 259.99997 180.00002-->
   16550 <!-- 262.02692 182.7661-->
   10815 <!-- 262.88434 182.05101-->
   47397 <!-- 245.37437 202.37842-->
   51868 <!-- 245.53374 203.01067-->
   10702 <!-- 248.03223 202.28374-->
   51868 <!-- 245.53374 203.01067-->
   50087 <!-- 245.94899 203.70602-->
   10702 <!-- 248.03223 202.28374-->
   51868 <!-- 245.53374 203.01067-->
   50589 <!-- 245.43805 203.42157-->
   50087 <!-- 245.94899 203.70602-->
   50087 <!-- 245.94899 203.70602-->
   14667 <!-- 247.87244 204.27493-->
   10702 <!-- 248.03223 202.28374-->
   50087 <!-- 245.94899 203.70602-->
   10231 <!-- 246.07632 204.0536-->
   14667 <!-- 247.87244 204.27493-->
   10231 <!-- 246.07632 204.0536-->
   41512 <!-- 246.04391 205.00009-->
   14667 <!-- 247.87244 204.27493-->
   41512 <!-- 246.04391 205.00009-->
   14384 <!-- 248.22362 205.00009-->
   14667 <!-- 247.87244 204.27493-->
   14384 <!-- 248.22362 205.00009-->
   41512 <!-- 246.04391 205.00009-->
   15419 <!-- 246.58688 205.91815-->
   18866 <!-- 248.06424 205.63388-->
   14384 <!-- 248.22362 205.00009-->
   15419 <!-- 246.58688 205.91815-->
   18866 <!-- 248.06424 205.63388-->
   15419 <!-- 246.58688 205.91815-->
   18038 <!-- 248.47908 206.4557-->
   18866 <!-- 248.06424 205.63388-->
   18038 <!-- 248.47908 206.4557-->
   19152 <!-- 248.51073 205.85522-->
   15419 <!-- 246.58688 205.91815-->
   45077 <!-- 246.71461 207.5618-->
   18038 <!-- 248.47908 206.4557-->
   45077 <!-- 246.71461 207.5618-->
   42789 <!-- 247.19351 207.97249-->
   18038 <!-- 248.47908 206.4557-->
   42789 <!-- 247.19351 207.97249-->
   51162 <!-- 248.60643 207.68842-->
   18038 <!-- 248.47908 206.4557-->
   42789 <!-- 247.19351 207.97249-->
   45587 <!-- 247.35289 209.01563-->
   51162 <!-- 248.60643 207.68842-->
   45587 <!-- 247.35289 209.01563-->
   51678 <!-- 249.11736 207.87779-->
   51162 <!-- 248.60643 207.68842-->
   45587 <!-- 247.35289 209.01563-->
   48903 <!-- 248.45544 209.71098-->
   44749 <!-- 248.83864 209.6161-->
   45587 <!-- 247.35289 209.01563-->
   44749 <!-- 248.83864 209.6161-->
   51678 <!-- 249.11736 207.87779-->
   10270 <!-- 264.46442 175.92747-->
   7012 <!-- 264.99957 174.99991-->
   55528 <!-- 259.99997 174.99991-->
   10270 <!-- 264.46442 175.92747-->
   9282 <!-- 264.99957 175.65938-->
   7012 <!-- 264.99957 174.99991-->
   9245 <!-- 264.32925 176.50859-->
   10270 <!-- 264.46442 175.92747-->
   55528 <!-- 259.99997 174.99991-->
   9245 <!-- 264.32925 176.50859-->
   55528 <!-- 259.99997 174.99991-->
   8175 <!-- 264.99957 177.17241-->
   55528 <!-- 259.99997 174.99991-->
   11201 <!-- 264.99997 178.92235-->
   8175 <!-- 264.99957 177.17241-->
   12395 <!-- 262.83942 181.29112-->
   14180 <!-- 259.99997 180.00002-->
   10815 <!-- 262.88434 182.05101-->
   12395 <!-- 262.83942 181.29112-->
   7025 <!-- 264.19373 180.00021-->
   14180 <!-- 259.99997 180.00002-->
   14180 <!-- 259.99997 180.00002-->
   7025 <!-- 264.19373 180.00021-->
   9021 <!-- 264.37457 179.45833-->
   55528 <!-- 259.99997 174.99991-->
   14180 <!-- 259.99997 180.00002-->
   9021 <!-- 264.37457 179.45833-->
   55528 <!-- 259.99997 174.99991-->
   9021 <!-- 264.37457 179.45833-->
   11201 <!-- 264.99997 178.92235-->
   56279 <!-- 238.84685 195.77278-->
   50226 <!-- 238.81522 196.94237-->
   980 <!-- 239.99957 196.31015-->
   56279 <!-- 238.84685 195.77278-->
   980 <!-- 239.99957 196.31015-->
   58362 <!-- 239.35739 195.52031-->
   55505 <!-- 239.99997 194.99989-->
   16 <!-- 239.54959 194.99989-->
   58362 <!-- 239.35739 195.52031-->
   980 <!-- 239.99957 196.31015-->
   55505 <!-- 239.99997 194.99989-->
   58362 <!-- 239.35739 195.52031-->
   16 <!-- 239.54959 194.99989-->
   55505 <!-- 239.99997 194.99989-->
   5941 <!-- 239.99957 194.3438-->
   55505 <!-- 239.99997 194.99989-->
   5760 <!-- 240.39568 194.00845-->
   5941 <!-- 239.99957 194.3438-->
   5760 <!-- 240.39568 194.00845-->
   55505 <!-- 239.99997 194.99989-->
   7056 <!-- 244.99959 195.00009-->
   5760 <!-- 240.39568 194.00845-->
   11852 <!-- 241.14021 192.64532-->
   1584 <!-- 240.57654 192.91362-->
   5760 <!-- 240.39568 194.00845-->
   7056 <!-- 244.99959 195.00009-->
   11852 <!-- 241.14021 192.64532-->
   7056 <!-- 244.99959 195.00009-->
   3208 <!-- 241.25386 191.90796-->
   11852 <!-- 241.14021 192.64532-->
   7056 <!-- 244.99959 195.00009-->
   3505 <!-- 241.63669 191.39389-->
   3208 <!-- 241.25386 191.90796-->
   55132 <!-- 244.99997 189.9998-->
   4958 <!-- 241.70467 189.99998-->
   3505 <!-- 241.63669 191.39389-->
   7056 <!-- 244.99959 195.00009-->
   55132 <!-- 244.99997 189.9998-->
   3505 <!-- 241.63669 191.39389-->
   55132 <!-- 244.99997 189.9998-->
   7056 <!-- 244.99959 195.00009-->
   17650 <!-- 249.99995 195.00009-->
   17650 <!-- 249.99995 195.00009-->
   28745 <!-- 249.99995 189.99998-->
   55132 <!-- 244.99997 189.9998-->
   55488 <!-- 249.99995 184.99991-->
   29099 <!-- 244.99997 185.00011-->
   55132 <!-- 244.99997 189.9998-->
   55132 <!-- 244.99997 189.9998-->
   28745 <!-- 249.99995 189.99998-->
   55488 <!-- 249.99995 184.99991-->
   55848 <!-- 254.99959 180.00002-->
   7428 <!-- 249.99995 180.00021-->
   55488 <!-- 249.99995 184.99991-->
   55488 <!-- 249.99995 184.99991-->
   7678 <!-- 254.99997 185.00031-->
   55848 <!-- 254.99959 180.00002-->
   55488 <!-- 249.99995 184.99991-->
   28745 <!-- 249.99995 189.99998-->
   18632 <!-- 254.99959 190.0002-->
   18632 <!-- 254.99959 190.0002-->
   7678 <!-- 254.99997 185.00031-->
   55488 <!-- 249.99995 184.99991-->
   55848 <!-- 254.99959 180.00002-->
   7678 <!-- 254.99997 185.00031-->
   3100 <!-- 259.99957 185.00011-->
   3100 <!-- 259.99957 185.00011-->
   14180 <!-- 259.99997 180.00002-->
   55848 <!-- 254.99959 180.00002-->
   2746 <!-- 254.99997 170.00003-->
   13815 <!-- 254.99959 175.00012-->
   55528 <!-- 259.99997 174.99991-->
   55528 <!-- 259.99997 174.99991-->
   7424 <!-- 259.99957 170.00021-->
   2746 <!-- 254.99997 170.00003-->
   55528 <!-- 259.99997 174.99991-->
   13815 <!-- 254.99959 175.00012-->
   55848 <!-- 254.99959 180.00002-->
   55848 <!-- 254.99959 180.00002-->
   14180 <!-- 259.99997 180.00002-->
   55528 <!-- 259.99997 174.99991-->
   2746 <!-- 254.99997 170.00003-->
   7424 <!-- 259.99957 170.00021-->
   17680 <!-- 259.99997 164.99994-->
   17680 <!-- 259.99997 164.99994-->
   7424 <!-- 259.99957 170.00021-->
   55071 <!-- 264.99957 170.00003-->
   55071 <!-- 264.99957 170.00003-->
   29057 <!-- 264.99957 164.99994-->
   17680 <!-- 259.99997 164.99994-->
   55071 <!-- 264.99957 170.00003-->
   7424 <!-- 259.99957 170.00021-->
   55528 <!-- 259.99997 174.99991-->
   55528 <!-- 259.99997 174.99991-->
   7012 <!-- 264.99957 174.99991-->
   55071 <!-- 264.99957 170.00003-->
   18026 <!-- 264.99997 160.00024-->
   28781 <!-- 259.99957 160.00024-->
   17680 <!-- 259.99997 164.99994-->
   17680 <!-- 259.99997 164.99994-->
   29057 <!-- 264.99957 164.99994-->
   18026 <!-- 264.99997 160.00024-->
   18026 <!-- 264.99997 160.00024-->
   29057 <!-- 264.99957 164.99994-->
   55450 <!-- 269.99957 165.00014-->
   55450 <!-- 269.99957 165.00014-->
   29057 <!-- 264.99957 164.99994-->
   55071 <!-- 264.99957 170.00003-->
   55450 <!-- 269.99957 165.00014-->
   7347 <!-- 269.99997 160.00024-->
   18026 <!-- 264.99997 160.00024-->
   55071 <!-- 264.99957 170.00003-->
   28709 <!-- 269.99957 170.00003-->
   55450 <!-- 269.99957 165.00014-->
   55450 <!-- 269.99957 165.00014-->
   9032 <!-- 274.99957 164.99994-->
   57201 <!-- 274.99957 160.00005-->
   57201 <!-- 274.99957 160.00005-->
   7347 <!-- 269.99997 160.00024-->
   55450 <!-- 269.99957 165.00014-->
   17680 <!-- 259.99997 164.99994-->
   50603 <!-- 254.99959 165.00014-->
   2746 <!-- 254.99997 170.00003-->
   58117 <!-- 264.99957 150.73112-->
   21561 <!-- 264.99997 154.99995-->
   54234 <!-- 269.99997 154.99995-->
   54234 <!-- 269.99997 154.99995-->
   21561 <!-- 264.99997 154.99995-->
   18026 <!-- 264.99997 160.00024-->
   18026 <!-- 264.99997 160.00024-->
   7347 <!-- 269.99997 160.00024-->
   54234 <!-- 269.99997 154.99995-->
   54234 <!-- 269.99997 154.99995-->
   7347 <!-- 269.99997 160.00024-->
   57201 <!-- 274.99957 160.00005-->
   57201 <!-- 274.99957 160.00005-->
   41362 <!-- 274.99997 155.00015-->
   54234 <!-- 269.99997 154.99995-->
   54234 <!-- 269.99997 154.99995-->
   41362 <!-- 274.99997 155.00015-->
   19522 <!-- 274.99997 150.00026-->
   58021 <!-- 274.99997 145.00035-->
   32607 <!-- 269.99997 150.00006-->
   19522 <!-- 274.99997 150.00026-->
   19522 <!-- 274.99997 150.00026-->
   32607 <!-- 269.99997 150.00006-->
   54234 <!-- 269.99997 154.99995-->
   58021 <!-- 274.99997 145.00035-->
   40532 <!-- 264.99997 149.34554-->
   39094 <!-- 265.64215 149.47948-->
   32607 <!-- 269.99997 150.00006-->
   58021 <!-- 274.99997 145.00035-->
   39094 <!-- 265.64215 149.47948-->
   41917 <!-- 265.68707 150.00026-->
   32607 <!-- 269.99997 150.00006-->
   39094 <!-- 265.64215 149.47948-->
   57450 <!-- 265.28122 140.00006-->
   36108 <!-- 264.99997 144.99997-->
   58021 <!-- 274.99997 145.00035-->
   58021 <!-- 274.99997 145.00035-->
   36108 <!-- 264.99997 144.99997-->
   40532 <!-- 264.99997 149.34554-->
   58021 <!-- 274.99997 145.00035-->
   24457 <!-- 279.99997 140.00006-->
   57450 <!-- 265.28122 140.00006-->
   57450 <!-- 265.28122 140.00006-->
   24457 <!-- 279.99997 140.00006-->
   23003 <!-- 267.16248 133.29462-->
   24457 <!-- 279.99997 140.00006-->
   22331 <!-- 267.59332 133.04784-->
   23003 <!-- 267.16248 133.29462-->
   24457 <!-- 279.99997 140.00006-->
   57935 <!-- 272.90582 130.00186-->
   22331 <!-- 267.59332 133.04784-->
   24457 <!-- 279.99997 140.00006-->
   18990 <!-- 275.71442 126.49704-->
   57935 <!-- 272.90582 130.00186-->
   24457 <!-- 279.99997 140.00006-->
   54312 <!-- 279.99997 120.00029-->
   18990 <!-- 275.71442 126.49704-->
   54312 <!-- 279.99997 120.00029-->
   24457 <!-- 279.99997 140.00006-->
   43929 <!-- 293.10931 132.8488-->
   24457 <!-- 279.99997 140.00006-->
   55576 <!-- 290.60309 140.00026-->
   43929 <!-- 293.10931 132.8488-->
   37229 <!-- 297.24759 127.23461-->
   54312 <!-- 279.99997 120.00029-->
   43929 <!-- 293.10931 132.8488-->
   37229 <!-- 297.24759 127.23461-->
   9893 <!-- 299.99954 120.00029-->
   54312 <!-- 279.99997 120.00029-->
   37229 <!-- 297.24759 127.23461-->
   42585 <!-- 299.99954 124.6165-->
   9893 <!-- 299.99954 120.00029-->
   54312 <!-- 279.99997 120.00029-->
   58279 <!-- 277.31247 120.00601-->
   18990 <!-- 275.71442 126.49704-->
   58279 <!-- 277.31247 120.00601-->
   54312 <!-- 279.99997 120.00029-->
   19649 <!-- 279.99997 113.22343-->
   19649 <!-- 279.99997 113.22343-->
   9893 <!-- 299.99954 120.00029-->
   37937 <!-- 280.84372 111.09335-->
   19649 <!-- 279.99997 113.22343-->
   54312 <!-- 279.99997 120.00029-->
   9893 <!-- 299.99954 120.00029-->
   9893 <!-- 299.99954 120.00029-->
   29541 <!-- 285.14175 108.865234375-->
   37937 <!-- 280.84372 111.09335-->
   9893 <!-- 299.99954 120.00029-->
   22824 <!-- 289.3605 105.72655487060547-->
   29541 <!-- 285.14175 108.865234375-->
   9893 <!-- 299.99954 120.00029-->
   15031 <!-- 293.73236 104.08746-->
   22824 <!-- 289.3605 105.72655487060547-->
   33876 <!-- 299.99994 100.00012-->
   43527 <!-- 295.823 100.00584411621094-->
   15031 <!-- 293.73236 104.08746-->
   43527 <!-- 295.823 100.00584411621094-->
   33876 <!-- 299.99994 100.00012-->
   23331 <!-- 299.99994 97.13997-->
   9893 <!-- 299.99954 120.00029-->
   33876 <!-- 299.99994 100.00012-->
   15031 <!-- 293.73236 104.08746-->
   33876 <!-- 299.99994 100.00012-->
   9893 <!-- 299.99954 120.00029-->
   11887 <!-- 305.02652 104.16736-->
   56575 <!-- 303.48431 119.99989-->
   9893 <!-- 299.99954 120.00029-->
   42585 <!-- 299.99954 124.6165-->
   9893 <!-- 299.99954 120.00029-->
   56575 <!-- 303.48431 119.99989-->
   11887 <!-- 305.02652 104.16736-->
   23331 <!-- 299.99994 97.13997-->
   33876 <!-- 299.99994 100.00012-->
   18267 <!-- 307.0097 100.00032-->
   18267 <!-- 307.0097 100.00032-->
   33876 <!-- 299.99994 100.00012-->
   11887 <!-- 305.02652 104.16736-->
   17394 <!-- 302.21478 94.50844-->
   23331 <!-- 299.99994 97.13997-->
   18267 <!-- 307.0097 100.00032-->
   17394 <!-- 302.21478 94.50844-->
   18267 <!-- 307.0097 100.00032-->
   51904 <!-- 308.10461 95.24285-->
   34026 <!-- 306.99683 90.82687-->
   17394 <!-- 302.21478 94.50844-->
   51904 <!-- 308.10461 95.24285-->
   56767 <!-- 309.36478 86.26195-->
   34026 <!-- 306.99683 90.82687-->
   22147 <!-- 311.02142 90.13978576660156-->
   34026 <!-- 306.99683 90.82687-->
   51904 <!-- 308.10461 95.24285-->
   22147 <!-- 311.02142 90.13978576660156-->
   58021 <!-- 274.99997 145.00035-->
   3255 <!-- 279.99997 144.99997-->
   24457 <!-- 279.99997 140.00006-->
   33233 <!-- 244.41286 185.00011-->
   29099 <!-- 244.99997 185.00011-->
   38818 <!-- 244.99997 184.19763-->
   13375 <!-- 246.73825 181.62766-->
   38818 <!-- 244.99997 184.19763-->
   55488 <!-- 249.99995 184.99991-->
   13375 <!-- 246.73825 181.62766-->
   55488 <!-- 249.99995 184.99991-->
   12475 <!-- 247.39294 180.00021-->
   38818 <!-- 244.99997 184.19763-->
   29099 <!-- 244.99997 185.00011-->
   55488 <!-- 249.99995 184.99991-->
   55488 <!-- 249.99995 184.99991-->
   7428 <!-- 249.99995 180.00021-->
   12475 <!-- 247.39294 180.00021-->
   16705 <!-- 248.58943 178.25304-->
   12475 <!-- 247.39294 180.00021-->
   7428 <!-- 249.99995 180.00021-->
   16705 <!-- 248.58943 178.25304-->
   7428 <!-- 249.99995 180.00021-->
   4891 <!-- 249.13045 176.88972-->
   7428 <!-- 249.99995 180.00021-->
   4023 <!-- 249.99957 175.817-->
   4891 <!-- 249.13045 176.88972-->
   4023 <!-- 249.99957 175.817-->
   55848 <!-- 254.99959 180.00002-->
   3776 <!-- 250.23669 175.54872-->
   4023 <!-- 249.99957 175.817-->
   7428 <!-- 249.99995 180.00021-->
   55848 <!-- 254.99959 180.00002-->
   13815 <!-- 254.99959 175.00012-->
   2652 <!-- 250.26755 175.00012-->
   3776 <!-- 250.23669 175.54872-->
   55848 <!-- 254.99959 180.00002-->
   13815 <!-- 254.99959 175.00012-->
   3776 <!-- 250.23669 175.54872-->
   1564 <!-- 252.45973 167.09016-->
   8496 <!-- 252.36987 170.00021-->
   6000 <!-- 253.7355 170.00021-->
   8577 <!-- 252.74216 170.29712-->
   6000 <!-- 253.7355 170.00021-->
   8496 <!-- 252.36987 170.00021-->
   597 <!-- 252.9113 166.77728-->
   1564 <!-- 252.45973 167.09016-->
   6000 <!-- 253.7355 170.00021-->
   2746 <!-- 254.99997 170.00003-->
   57370 <!-- 253.04723 165.57024-->
   597 <!-- 252.9113 166.77728-->
   2746 <!-- 254.99997 170.00003-->
   55907 <!-- 254.22067 165.00014-->
   57370 <!-- 253.04723 165.57024-->
   2746 <!-- 254.99997 170.00003-->
   597 <!-- 252.9113 166.77728-->
   6000 <!-- 253.7355 170.00021-->
   55907 <!-- 254.22067 165.00014-->
   50603 <!-- 254.99959 165.00014-->
   56182 <!-- 253.63394 164.22942-->
   2746 <!-- 254.99997 170.00003-->
   50603 <!-- 254.99959 165.00014-->
   55907 <!-- 254.22067 165.00014-->
   756 <!-- 254.26598 163.06732-->
   1702 <!-- 253.67888 163.29063-->
   56182 <!-- 253.63394 164.22942-->
   50603 <!-- 254.99959 165.00014-->
   756 <!-- 254.26598 163.06732-->
   56182 <!-- 253.63394 164.22942-->
   50603 <!-- 254.99959 165.00014-->
   44462 <!-- 254.99959 162.26306-->
   756 <!-- 254.26598 163.06732-->
   44462 <!-- 254.99959 162.26306-->
   17680 <!-- 259.99997 164.99994-->
   44024 <!-- 255.89137 161.72652-->
   44462 <!-- 254.99959 162.26306-->
   50603 <!-- 254.99959 165.00014-->
   17680 <!-- 259.99997 164.99994-->
   17680 <!-- 259.99997 164.99994-->
   36292 <!-- 256.97418 161.72652-->
   44024 <!-- 255.89137 161.72652-->
   17680 <!-- 259.99997 164.99994-->
   34214 <!-- 257.832 160.87749-->
   36292 <!-- 256.97418 161.72652-->
   28781 <!-- 259.99957 160.00024-->
   31914 <!-- 258.37381 160.00005-->
   34214 <!-- 257.832 160.87749-->
   17680 <!-- 259.99997 164.99994-->
   28781 <!-- 259.99957 160.00024-->
   34214 <!-- 257.832 160.87749-->
   34022 <!-- 259.32184 159.35753-->
   31914 <!-- 258.37381 160.00005-->
   28781 <!-- 259.99957 160.00024-->
   28781 <!-- 259.99957 160.00024-->
   36438 <!-- 259.99997 158.59769-->
   34022 <!-- 259.32184 159.35753-->
   36438 <!-- 259.99997 158.59769-->
   28781 <!-- 259.99957 160.00024-->
   18026 <!-- 264.99997 160.00024-->
   36346 <!-- 262.34644 156.944-->
   36438 <!-- 259.99997 158.59769-->
   18026 <!-- 264.99997 160.00024-->
   36346 <!-- 262.34644 156.944-->
   18026 <!-- 264.99997 160.00024-->
   21561 <!-- 264.99997 154.99995-->
   36346 <!-- 262.34644 156.944-->
   21561 <!-- 264.99997 154.99995-->
   27219 <!-- 262.43707 154.99995-->
   27219 <!-- 262.43707 154.99995-->
   21561 <!-- 264.99997 154.99995-->
   21764 <!-- 262.61755 153.68123-->
   21561 <!-- 264.99997 154.99995-->
   49366 <!-- 263.5199 152.20607-->
   21764 <!-- 262.61755 153.68123-->
   21561 <!-- 264.99997 154.99995-->
   58117 <!-- 264.99957 150.73112-->
   49366 <!-- 263.5199 152.20607-->
   58117 <!-- 264.99957 150.73112-->
   32607 <!-- 269.99997 150.00006-->
   41917 <!-- 265.68707 150.00026-->
   58117 <!-- 264.99957 150.73112-->
   54234 <!-- 269.99997 154.99995-->
   32607 <!-- 269.99997 150.00006-->
   56984 <!-- 242.4949 188.08633-->
   4958 <!-- 241.70467 189.99998-->
   55132 <!-- 244.99997 189.9998-->
   33233 <!-- 244.41286 185.00011-->
   56984 <!-- 242.4949 188.08633-->
   55132 <!-- 244.99997 189.9998-->
   33233 <!-- 244.41286 185.00011-->
   55132 <!-- 244.99997 189.9998-->
   29099 <!-- 244.99997 185.00011-->
   52250 <!-- 244.72789 202.22061-->
   30921 <!-- 244.72751 201.24078-->
   52205 <!-- 244.51227 201.84146-->
   11975 <!-- 250.30426 174.34224-->
   2652 <!-- 250.26755 175.00012-->
   13815 <!-- 254.99959 175.00012-->
   17383 <!-- 251.07222 173.22455-->
   11975 <!-- 250.30426 174.34224-->
   13815 <!-- 254.99959 175.00012-->
   16907 <!-- 251.88472 172.95665-->
   17383 <!-- 251.07222 173.22455-->
   13815 <!-- 254.99959 175.00012-->
   12492 <!-- 252.44878 171.95079-->
   16907 <!-- 251.88472 172.95665-->
   13815 <!-- 254.99959 175.00012-->
   8586 <!-- 253.41951 171.01221-->
   12492 <!-- 252.44878 171.95079-->
   13815 <!-- 254.99959 175.00012-->
   5620 <!-- 254.3902 170.65436-->
   8586 <!-- 253.41951 171.01221-->
   13815 <!-- 254.99959 175.00012-->
   7665 <!-- 254.59294 170.23004-->
   5620 <!-- 254.3902 170.65436-->
   13815 <!-- 254.99959 175.00012-->
   6000 <!-- 253.7355 170.00021-->
   7665 <!-- 254.59294 170.23004-->
   2746 <!-- 254.99997 170.00003-->
   7665 <!-- 254.59294 170.23004-->
   13815 <!-- 254.99959 175.00012-->
   2746 <!-- 254.99997 170.00003-->
   42881 <!-- 264.4234 147.33441-->
   43056 <!-- 264.24292 149.07724-->
   40532 <!-- 264.99997 149.34554-->
   44015 <!-- 264.6488 146.93198-->
   42881 <!-- 264.4234 147.33441-->
   40532 <!-- 264.99997 149.34554-->
   44015 <!-- 264.6488 146.93198-->
   40532 <!-- 264.99997 149.34554-->
   36108 <!-- 264.99997 144.99997-->
   8175 <!-- 264.99957 177.17241-->
   11201 <!-- 264.99997 178.92235-->
   9459 <!-- 265.41248 177.58115-->
   8501 <!-- 265.63824 175.00012-->
   7012 <!-- 264.99957 174.99991-->
   9282 <!-- 264.99957 175.65938-->
   55071 <!-- 264.99957 170.00003-->
   7012 <!-- 264.99957 174.99991-->
   18804 <!-- 266.22498 173.91617-->
   7012 <!-- 264.99957 174.99991-->
   8501 <!-- 265.63824 175.00012-->
   18804 <!-- 266.22498 173.91617-->
   55071 <!-- 264.99957 170.00003-->
   18804 <!-- 266.22498 173.91617-->
   21388 <!-- 266.40582 173.02234-->
   55071 <!-- 264.99957 170.00003-->
   21388 <!-- 266.40582 173.02234-->
   18333 <!-- 267.26364 172.48578-->
   55071 <!-- 264.99957 170.00003-->
   18333 <!-- 267.26364 172.48578-->
   25891 <!-- 268.61755 172.39641-->
   32224 <!-- 269.99997 171.45764-->
   28709 <!-- 269.99957 170.00003-->
   55071 <!-- 264.99957 170.00003-->
   55071 <!-- 264.99957 170.00003-->
   25891 <!-- 268.61755 172.39641-->
   28985 <!-- 268.97888 171.9494-->
   32224 <!-- 269.99997 171.45764-->
   55071 <!-- 264.99957 170.00003-->
   28985 <!-- 268.97888 171.9494-->
   55450 <!-- 269.99957 165.00014-->
   28709 <!-- 269.99957 170.00003-->
   23339 <!-- 272.45505 170.00003-->
   23339 <!-- 272.45505 170.00003-->
   28709 <!-- 269.99957 170.00003-->
   32224 <!-- 269.99997 171.45764-->
   11306 <!-- 274.99997 166.63072-->
   9032 <!-- 274.99957 164.99994-->
   55450 <!-- 269.99957 165.00014-->
   55450 <!-- 269.99957 165.00014-->
   23339 <!-- 272.45505 170.00003-->
   26251 <!-- 273.80933 168.46335-->
   11306 <!-- 274.99997 166.63072-->
   55450 <!-- 269.99957 165.00014-->
   26251 <!-- 273.80933 168.46335-->
   9032 <!-- 274.99957 164.99994-->
   11306 <!-- 274.99997 166.63072-->
   9354 <!-- 275.2988 165.46844-->
   9354 <!-- 275.2988 165.46844-->
   39676 <!-- 275.79565 164.99994-->
   9032 <!-- 274.99957 164.99994-->
   57201 <!-- 274.99957 160.00005-->
   9032 <!-- 274.99957 164.99994-->
   39676 <!-- 275.79565 164.99994-->
   57201 <!-- 274.99957 160.00005-->
   39676 <!-- 275.79565 164.99994-->
   35175 <!-- 276.60855 162.83139-->
   57201 <!-- 274.99957 160.00005-->
   35175 <!-- 276.60855 162.83139-->
   46718 <!-- 277.69138 161.08836-->
   57201 <!-- 274.99957 160.00005-->
   44592 <!-- 278.0527 160.00005-->
   41298 <!-- 277.87222 158.13844-->
   44592 <!-- 278.0527 160.00005-->
   57201 <!-- 274.99957 160.00005-->
   46718 <!-- 277.69138 161.08836-->
   7905 <!-- 276.83395 156.12692-->
   41362 <!-- 274.99997 155.00015-->
   57201 <!-- 274.99957 160.00005-->
   7905 <!-- 276.83395 156.12692-->
   23327 <!-- 277.51129 155.00015-->
   41362 <!-- 274.99997 155.00015-->
   7905 <!-- 276.83395 156.12692-->
   57201 <!-- 274.99957 160.00005-->
   41298 <!-- 277.87222 158.13844-->
   41362 <!-- 274.99997 155.00015-->
   23327 <!-- 277.51129 155.00015-->
   19595 <!-- 278.05307 154.16019-->
   41362 <!-- 274.99997 155.00015-->
   19595 <!-- 278.05307 154.16019-->
   25397 <!-- 278.27847 152.90854-->
   19522 <!-- 274.99997 150.00026-->
   41362 <!-- 274.99997 155.00015-->
   25397 <!-- 278.27847 152.90854-->
   33341 <!-- 278.14291 151.1655-->
   19522 <!-- 274.99997 150.00026-->
   25397 <!-- 278.27847 152.90854-->
   25521 <!-- 278.45932 152.01453-->
   33341 <!-- 278.14291 151.1655-->
   25397 <!-- 278.27847 152.90854-->
   33341 <!-- 278.14291 151.1655-->
   36891 <!-- 278.8652 150.00006-->
   19522 <!-- 274.99997 150.00026-->
   46322 <!-- 279.99997 148.48347-->
   3255 <!-- 279.99997 144.99997-->
   58021 <!-- 274.99997 145.00035-->
   46322 <!-- 279.99997 148.48347-->
   58021 <!-- 274.99997 145.00035-->
   19522 <!-- 274.99997 150.00026-->
   46322 <!-- 279.99997 148.48347-->
   19522 <!-- 274.99997 150.00026-->
   36891 <!-- 278.8652 150.00006-->
   3255 <!-- 279.99997 144.99997-->
   46322 <!-- 279.99997 148.48347-->
   2688 <!-- 281.84488 146.02534-->
   2688 <!-- 281.84488 146.02534-->
   49647 <!-- 283.15387 145.00017-->
   3255 <!-- 279.99997 144.99997-->
   24457 <!-- 279.99997 140.00006-->
   3255 <!-- 279.99997 144.99997-->
   49647 <!-- 283.15387 145.00017-->
   24457 <!-- 279.99997 140.00006-->
   49647 <!-- 283.15387 145.00017-->
   47227 <!-- 284.32806 144.14816-->
   55986 <!-- 284.99957 143.92467-->
   24457 <!-- 279.99997 140.00006-->
   47227 <!-- 284.32806 144.14816-->
   24457 <!-- 279.99997 140.00006-->
   55986 <!-- 284.99957 143.92467-->
   21108 <!-- 287.12653 142.80736-->
   24457 <!-- 279.99997 140.00006-->
   21108 <!-- 287.12653 142.80736-->
   52681 <!-- 288.61636 141.60028-->
   24457 <!-- 279.99997 140.00006-->
   52681 <!-- 288.61636 141.60028-->
   55852 <!-- 289.02301 140.6617-->
   55576 <!-- 290.60309 140.00026-->
   24457 <!-- 279.99997 140.00006-->
   55852 <!-- 289.02301 140.6617-->
   54265 <!-- 289.99994 140.57234-->
   55576 <!-- 290.60309 140.00026-->
   55852 <!-- 289.02301 140.6617-->
   25521 <!-- 278.45932 152.01453-->
   25397 <!-- 278.27847 152.90854-->
   25840 <!-- 278.77496 152.41714-->
  </u4_ary>
 </rec>
 <ary type="outlines">
  <rec type="outlines">
   <yes/>
   <v2 x="230.16444" y="86.26195"/>
   <v2 x="311.02142" y="212.93451"/>
   <u4_ary>
    31721 <!-- 231.79218 212.93451-->
    35542 <!-- 231.44139 212.77669-->
    28312 <!-- 231.18513 212.0182-->
    36337 <!-- 230.51561 211.48085-->
    35124 <!-- 230.16444 210.56436-->
    33008 <!-- 230.48358 210.00018-->
    22537 <!-- 231.88788 209.04738-->
    24069 <!-- 232.39879 207.62509-->
    17385 <!-- 232.36676 205.94992-->
    16233 <!-- 232.94177 204.99989-->
    17374 <!-- 233.73981 204.55939-->
    14537 <!-- 233.67577 203.32687-->
    16912 <!-- 234.4742 203.10536-->
    15504 <!-- 234.99959 202.34686-->
    50317 <!-- 236.90038 200.0-->
    44343 <!-- 238.62381 198.80714-->
    46572 <!-- 239.03865 198.11197-->
    46496 <!-- 239.99997 197.28996-->
    58380 <!-- 240.76208 196.6581-->
    889 <!-- 240.69841 195.80475-->
    980 <!-- 239.99957 196.31015-->
    50226 <!-- 238.81522 196.94237-->
    56279 <!-- 238.84685 195.77278-->
    58362 <!-- 239.35739 195.52031-->
    16 <!-- 239.54959 194.99989-->
    5941 <!-- 239.99957 194.3438-->
    5760 <!-- 240.39568 194.00845-->
    1584 <!-- 240.57654 192.91362-->
    11852 <!-- 241.14021 192.64532-->
    3208 <!-- 241.25386 191.90796-->
    3505 <!-- 241.63669 191.39389-->
    4958 <!-- 241.70467 189.99998-->
    56984 <!-- 242.4949 188.08633-->
    33233 <!-- 244.41286 185.00011-->
    38818 <!-- 244.99997 184.19763-->
    13375 <!-- 246.73825 181.62766-->
    12475 <!-- 247.39294 180.00021-->
    16705 <!-- 248.58943 178.25304-->
    4891 <!-- 249.13045 176.88972-->
    4023 <!-- 249.99957 175.817-->
    3776 <!-- 250.23669 175.54872-->
    2652 <!-- 250.26755 175.00012-->
    11975 <!-- 250.30426 174.34224-->
    17383 <!-- 251.07222 173.22455-->
    16907 <!-- 251.88472 172.95665-->
    12492 <!-- 252.44878 171.95079-->
    8586 <!-- 253.41951 171.01221-->
    5620 <!-- 254.3902 170.65436-->
    7665 <!-- 254.59294 170.23004-->
    6000 <!-- 253.7355 170.00021-->
    8577 <!-- 252.74216 170.29712-->
    8496 <!-- 252.36987 170.00021-->
    1564 <!-- 252.45973 167.09016-->
    597 <!-- 252.9113 166.77728-->
    57370 <!-- 253.04723 165.57024-->
    55907 <!-- 254.22067 165.00014-->
    56182 <!-- 253.63394 164.22942-->
    1702 <!-- 253.67888 163.29063-->
    756 <!-- 254.26598 163.06732-->
    44462 <!-- 254.99959 162.26306-->
    44024 <!-- 255.89137 161.72652-->
    36292 <!-- 256.97418 161.72652-->
    34214 <!-- 257.832 160.87749-->
    31914 <!-- 258.37381 160.00005-->
    34022 <!-- 259.32184 159.35753-->
    36438 <!-- 259.99997 158.59769-->
    36346 <!-- 262.34644 156.944-->
    27219 <!-- 262.43707 154.99995-->
    21764 <!-- 262.61755 153.68123-->
    49366 <!-- 263.5199 152.20607-->
    58117 <!-- 264.99957 150.73112-->
    41917 <!-- 265.68707 150.00026-->
    39094 <!-- 265.64215 149.47948-->
    40532 <!-- 264.99997 149.34554-->
    43056 <!-- 264.24292 149.07724-->
    42881 <!-- 264.4234 147.33441-->
    44015 <!-- 264.6488 146.93198-->
    36108 <!-- 264.99997 144.99997-->
    57450 <!-- 265.28122 140.00006-->
    23003 <!-- 267.16248 133.29462-->
    22331 <!-- 267.59332 133.04784-->
    57935 <!-- 272.90582 130.00186-->
    18990 <!-- 275.71442 126.49704-->
    58279 <!-- 277.31247 120.00601-->
    19649 <!-- 279.99997 113.22343-->
    37937 <!-- 280.84372 111.09335-->
    29541 <!-- 285.14175 108.865234375-->
    22824 <!-- 289.3605 105.72655487060547-->
    15031 <!-- 293.73236 104.08746-->
    43527 <!-- 295.823 100.00584411621094-->
    23331 <!-- 299.99994 97.13997-->
    17394 <!-- 302.21478 94.50844-->
    34026 <!-- 306.99683 90.82687-->
    56767 <!-- 309.36478 86.26195-->
    22147 <!-- 311.02142 90.13978576660156-->
    51904 <!-- 308.10461 95.24285-->
    18267 <!-- 307.0097 100.00032-->
    11887 <!-- 305.02652 104.16736-->
    56575 <!-- 303.48431 119.99989-->
    42585 <!-- 299.99954 124.6165-->
    37229 <!-- 297.24759 127.23461-->
    43929 <!-- 293.10931 132.8488-->
    55576 <!-- 290.60309 140.00026-->
    54265 <!-- 289.99994 140.57234-->
    55852 <!-- 289.02301 140.6617-->
    52681 <!-- 288.61636 141.60028-->
    21108 <!-- 287.12653 142.80736-->
    55986 <!-- 284.99957 143.92467-->
    47227 <!-- 284.32806 144.14816-->
    49647 <!-- 283.15387 145.00017-->
    2688 <!-- 281.84488 146.02534-->
    46322 <!-- 279.99997 148.48347-->
    36891 <!-- 278.8652 150.00006-->
    33341 <!-- 278.14291 151.1655-->
    25521 <!-- 278.45932 152.01453-->
    25840 <!-- 278.77496 152.41714-->
    25397 <!-- 278.27847 152.90854-->
    19595 <!-- 278.05307 154.16019-->
    23327 <!-- 277.51129 155.00015-->
    7905 <!-- 276.83395 156.12692-->
    41298 <!-- 277.87222 158.13844-->
    44592 <!-- 278.0527 160.00005-->
    46718 <!-- 277.69138 161.08836-->
    35175 <!-- 276.60855 162.83139-->
    39676 <!-- 275.79565 164.99994-->
    9354 <!-- 275.2988 165.46844-->
    11306 <!-- 274.99997 166.63072-->
    26251 <!-- 273.80933 168.46335-->
    23339 <!-- 272.45505 170.00003-->
    32224 <!-- 269.99997 171.45764-->
    28985 <!-- 268.97888 171.9494-->
    25891 <!-- 268.61755 172.39641-->
    18333 <!-- 267.26364 172.48578-->
    21388 <!-- 266.40582 173.02234-->
    18804 <!-- 266.22498 173.91617-->
    8501 <!-- 265.63824 175.00012-->
    9282 <!-- 264.99957 175.65938-->
    10270 <!-- 264.46442 175.92747-->
    9245 <!-- 264.32925 176.50859-->
    8175 <!-- 264.99957 177.17241-->
    9459 <!-- 265.41248 177.58115-->
    11201 <!-- 264.99997 178.92235-->
    9021 <!-- 264.37457 179.45833-->
    7025 <!-- 264.19373 180.00021-->
    12395 <!-- 262.83942 181.29112-->
    10815 <!-- 262.88434 182.05101-->
    16550 <!-- 262.02692 182.7661-->
    18253 <!-- 260.94333 182.94479-->
    13185 <!-- 260.5824 183.92816-->
    15339 <!-- 261.34998 184.46434-->
    21675 <!-- 261.07925 185.00031-->
    23738 <!-- 260.98865 185.17982-->
    4521 <!-- 259.99957 185.51636-->
    5985 <!-- 259.5437 185.6714-->
    56224 <!-- 257.37732 190.0002-->
    57391 <!-- 256.33865 191.21376-->
    34300 <!-- 254.99959 192.15257-->
    37230 <!-- 254.39723 192.91223-->
    34921 <!-- 254.35229 193.98495-->
    31350 <!-- 253.67537 195.00009-->
    36988 <!-- 252.63669 195.90692-->
    38234 <!-- 252.50192 196.62221-->
    10784 <!-- 251.01169 198.76747-->
    20328 <!-- 249.99995 199.50249-->
    23753 <!-- 249.19281 199.72382-->
    27189 <!-- 248.15993 199.53424-->
    20723 <!-- 247.13846 199.18607-->
    29938 <!-- 246.72362 199.37604-->
    29458 <!-- 246.59589 200.00018-->
    30067 <!-- 246.65955 200.45074-->
    26738 <!-- 247.1701 200.577-->
    9632 <!-- 247.42557 201.84126-->
    10702 <!-- 248.03223 202.28374-->
    14667 <!-- 247.87244 204.27493-->
    14384 <!-- 248.22362 205.00009-->
    18866 <!-- 248.06424 205.63388-->
    19152 <!-- 248.51073 205.85522-->
    18038 <!-- 248.47908 206.4557-->
    51162 <!-- 248.60643 207.68842-->
    51678 <!-- 249.11736 207.87779-->
    44749 <!-- 248.83864 209.6161-->
    48903 <!-- 248.45544 209.71098-->
    45587 <!-- 247.35289 209.01563-->
    42789 <!-- 247.19351 207.97249-->
    45077 <!-- 246.71461 207.5618-->
    15419 <!-- 246.58688 205.91815-->
    41512 <!-- 246.04391 205.00009-->
    10231 <!-- 246.07632 204.0536-->
    50087 <!-- 245.94899 203.70602-->
    50589 <!-- 245.43805 203.42157-->
    51868 <!-- 245.53374 203.01067-->
    47397 <!-- 245.37437 202.37842-->
    52250 <!-- 244.72789 202.22061-->
    52205 <!-- 244.51227 201.84146-->
    30921 <!-- 244.72751 201.24078-->
    32983 <!-- 245.08688 200.0-->
    31238 <!-- 244.99078 199.47093-->
    35793 <!-- 244.72751 198.90181-->
    36783 <!-- 244.22516 198.80693-->
    35724 <!-- 244.12906 198.26978-->
    36617 <!-- 243.74625 198.11176-->
    32623 <!-- 243.55446 197.38504-->
    32210 <!-- 243.28355 197.29016-->
    31717 <!-- 242.83708 197.6693-->
    33743 <!-- 241.94333 197.85887-->
    31419 <!-- 241.56013 198.39622-->
    50251 <!-- 240.63435 198.83867-->
    41722 <!-- 239.99957 199.43918-->
    44935 <!-- 239.51717 200.0-->
    41227 <!-- 239.2941 200.70363-->
    41391 <!-- 238.84685 200.89302-->
    50533 <!-- 238.39998 201.55701-->
    30706 <!-- 237.85742 201.77834-->
    30939 <!-- 237.50586 202.31509-->
    34330 <!-- 236.99567 202.53664-->
    31021 <!-- 236.74023 203.13731-->
    31672 <!-- 236.2617 203.29512-->
    40598 <!-- 236.22928 205.00009-->
    37938 <!-- 236.22928 206.20282-->
    12269 <!-- 235.62262 206.4557-->
    27896 <!-- 234.99959 207.30908-->
    30187 <!-- 233.96288 207.90956-->
    27218 <!-- 233.83513 208.88937-->
    23803 <!-- 233.48438 208.98405-->
    28320 <!-- 233.26054 209.3632-->
    27066 <!-- 232.8781 209.77411-->
    27923 <!-- 232.79333 210.00018-->
    27617 <!-- 232.65428 210.37479-->
    31937 <!-- 232.55858 211.7653-->
    35297 <!-- 232.01599 212.0182-->
   </u4_ary>
   <ary type="connectivity">
    <connectivity region="31 (egypt)" area="0" from="0" to="53"/>
    <connectivity region="14 (sahara)" area="0" from="54" to="79"/>
    <connectivity region="9 (central_africa)" area="0" from="80" to="92"/>
    <connectivity region="10 (arabian_sea)" area="0" from="93" to="93"/>
    <connectivity region="13 (arabia)" area="0" from="94" to="157"/>
    <connectivity region="36 (palestine)" area="0" from="158" to="229"/>
   </ary>
  </rec>
 </ary>
 <u2>0</u2><!-- Impassable Land Areas ID (65535=Passable) -->
 <u2>0</u2><!-- Island ID (65535=Navigable, 104=ETW Mainland) -->
</rec>
