<?xml version="1.0"?>
<rec type="areas">
 <no/><!-- Land Bridge -->
 <no/><!-- English Channel Coast -->
 <no/><!-- Passable -->
 <v2 x="225.97739" y="223.54385"/>
 <v2 x="226.49927" y="224.3356"/>
 <u2>268</u2><!-- Adjoning Passable Areas ID -->
 <rec type="faces">
  <u4_ary>
   48355 <!-- 226.16817 223.98557-->
   48602 <!-- 225.97739 224.2437-->
   49306 <!-- 226.3175 224.3356-->
   48355 <!-- 226.16817 223.98557-->
   49306 <!-- 226.3175 224.3356-->
   16006 <!-- 226.49927 223.8848-->
   56200 <!-- 226.1597 223.62891-->
   56028 <!-- 226.21135 223.74084-->
   16827 <!-- 226.44246 223.54385-->
   56028 <!-- 226.21135 223.74084-->
   48355 <!-- 226.16817 223.98557-->
   16006 <!-- 226.49927 223.8848-->
   56028 <!-- 226.21135 223.74084-->
   16006 <!-- 226.49927 223.8848-->
   16827 <!-- 226.44246 223.54385-->
  </u4_ary>
 </rec>
 <ary type="outlines">
  <rec type="outlines">
   <yes/>
   <v2 x="225.97739" y="223.54385"/>
   <v2 x="226.49927" y="224.3356"/>
   <u4_ary>
    48602 <!-- 225.97739 224.2437-->
    48355 <!-- 226.16817 223.98557-->
    56028 <!-- 226.21135 223.74084-->
    56200 <!-- 226.1597 223.62891-->
    16827 <!-- 226.44246 223.54385-->
    16006 <!-- 226.49927 223.8848-->
    49306 <!-- 226.3175 224.3356-->
   </u4_ary>
   <ary type="connectivity">
    <connectivity region="35 (egypt)" area="0" from="0" to="5"/>
    <connectivity region="48 (mediterranean_sea)" area="0" from="6" to="6"/>
   </ary>
  </rec>
 </ary>
 <u2>53</u2><!-- Impassable Land Areas ID (65535=Passable) -->
 <u2>35</u2><!-- Island ID (65535=Navigable, 104=ETW Mainland) -->
</rec>
