<?xml version="1.0"?>
<rec type="areas">
 <no/><!-- Land Bridge -->
 <no/><!-- English Channel Coast -->
 <no/><!-- Passable -->
 <v2 x="93.99498" y="269.64957"/>
 <v2 x="131.91565" y="305.39212"/>
 <u2>378</u2><!-- Adjoning Passable Areas ID -->
 <rec type="faces">
  <u4_ary>
   49917 <!-- 94.99982 302.82315-->
   727 <!-- 95.00004577636719 300.00006-->
   50677 <!-- 93.99498 301.14841-->
   49917 <!-- 94.99982 302.82315-->
   49142 <!-- 95.62676 303.86807-->
   6698 <!-- 96.71462 304.27603-->
   727 <!-- 95.00004577636719 300.00006-->
   49917 <!-- 94.99982 302.82315-->
   6698 <!-- 96.71462 304.27603-->
   9513 <!-- 99.99965 300.00006-->
   727 <!-- 95.00004577636719 300.00006-->
   6698 <!-- 96.71462 304.27603-->
   6698 <!-- 96.71462 304.27603-->
   58702 <!-- 97.53049 305.00015-->
   9101 <!-- 99.3559 304.15961-->
   58702 <!-- 97.53049 305.00015-->
   8218 <!-- 99.16411 305.00015-->
   9101 <!-- 99.3559 304.15961-->
   9513 <!-- 99.99965 300.00006-->
   6698 <!-- 96.71462 304.27603-->
   9101 <!-- 99.3559 304.15961-->
   1966 <!-- 99.99927 303.30624-->
   9513 <!-- 99.99965 300.00006-->
   9101 <!-- 99.3559 304.15961-->
   54393 <!-- 96.57865 299.1087-->
   727 <!-- 95.00004577636719 300.00006-->
   9513 <!-- 99.99965 300.00006-->
   54355 <!-- 97.74989 296.55255-->
   54393 <!-- 96.57865 299.1087-->
   9513 <!-- 99.99965 300.00006-->
   54355 <!-- 97.74989 296.55255-->
   20087 <!-- 99.99965 294.99997-->
   38280 <!-- 97.34943 295.00012-->
   54355 <!-- 97.74989 296.55255-->
   9513 <!-- 99.99965 300.00006-->
   20087 <!-- 99.99965 294.99997-->
   41209 <!-- 97.48994 293.89914-->
   36622 <!-- 98.05891418457031 292.92538-->
   43503 <!-- 96.95344 293.17117-->
   41209 <!-- 97.48994 293.89914-->
   38280 <!-- 97.34943 295.00012-->
   20087 <!-- 99.99965 294.99997-->
   41209 <!-- 97.48994 293.89914-->
   20087 <!-- 99.99965 294.99997-->
   36622 <!-- 98.05891418457031 292.92538-->
   20087 <!-- 99.99965 294.99997-->
   22632 <!-- 98.5788345336914 292.32193-->
   36622 <!-- 98.05891418457031 292.92538-->
   20087 <!-- 99.99965 294.99997-->
   21087 <!-- 99.55591 291.2825-->
   22632 <!-- 98.5788345336914 292.32193-->
   20087 <!-- 99.99965 294.99997-->
   29995 <!-- 99.99965 290.85797-->
   21087 <!-- 99.55591 291.2825-->
   21087 <!-- 99.55591 291.2825-->
   22542 <!-- 98.7438 291.79678-->
   22632 <!-- 98.5788345336914 292.32193-->
   48749 <!-- 104.99966 299.54517-->
   42605 <!-- 104.99966 295.00018-->
   20087 <!-- 99.99965 294.99997-->
   49260 <!-- 104.68677 300.00006-->
   20087 <!-- 99.99965 294.99997-->
   9513 <!-- 99.99965 300.00006-->
   49260 <!-- 104.68677 300.00006-->
   48749 <!-- 104.99966 299.54517-->
   20087 <!-- 99.99965 294.99997-->
   28025 <!-- 101.15864 290.09811-->
   31555 <!-- 100.18793487548828 290.1431-->
   29995 <!-- 99.99965 290.85797-->
   26172 <!-- 101.47426 290.3439-->
   28025 <!-- 101.15864 290.09811-->
   29995 <!-- 99.99965 290.85797-->
   26172 <!-- 101.47426 290.3439-->
   29995 <!-- 99.99965 290.85797-->
   42605 <!-- 104.99966 295.00018-->
   26172 <!-- 101.47426 290.3439-->
   42605 <!-- 104.99966 295.00018-->
   22063 <!-- 102.28715515136719 290.00009-->
   29995 <!-- 99.99965 290.85797-->
   20087 <!-- 99.99965 294.99997-->
   42605 <!-- 104.99966 295.00018-->
   42605 <!-- 104.99966 295.00018-->
   53488 <!-- 104.99926 290.00027-->
   22063 <!-- 102.28715515136719 290.00009-->
   53488 <!-- 104.99926 290.00027-->
   42605 <!-- 104.99966 295.00018-->
   37280 <!-- 109.99965 294.99997-->
   37280 <!-- 109.99965 294.99997-->
   47930 <!-- 109.99925 290.00009-->
   53488 <!-- 104.99926 290.00027-->
   36809 <!-- 107.78325 298.12329-->
   42605 <!-- 104.99966 295.00018-->
   48749 <!-- 104.99966 299.54517-->
   36809 <!-- 107.78325 298.12329-->
   37280 <!-- 109.99965 294.99997-->
   42605 <!-- 104.99966 295.00018-->
   36809 <!-- 107.78325 298.12329-->
   59964 <!-- 109.25159454345703 298.12289-->
   37280 <!-- 109.99965 294.99997-->
   59964 <!-- 109.25159454345703 298.12289-->
   57126 <!-- 109.99925 297.83844-->
   37280 <!-- 109.99965 294.99997-->
   9483 <!-- 114.99926 290.00009-->
   17138 <!-- 110.977 285.13687-->
   47930 <!-- 109.99925 290.00009-->
   9483 <!-- 114.99926 290.00009-->
   14844 <!-- 111.33871459960938 285.00018-->
   17138 <!-- 110.977 285.13687-->
   49565 <!-- 113.08246 295.59433-->
   37280 <!-- 109.99965 294.99997-->
   57126 <!-- 109.99925 297.83844-->
   33513 <!-- 113.33754 295.879-->
   49565 <!-- 113.08246 295.59433-->
   57126 <!-- 109.99925 297.83844-->
   40802 <!-- 114.48637 296.44791-->
   33513 <!-- 113.33754 295.879-->
   57126 <!-- 109.99925 297.83844-->
   49565 <!-- 113.08246 295.59433-->
   6593 <!-- 113.46527 294.99997-->
   37280 <!-- 109.99965 294.99997-->
   37389 <!-- 114.23128509521484 298.40753-->
   40802 <!-- 114.48637 296.44791-->
   57126 <!-- 109.99925 297.83844-->
   37389 <!-- 114.23128509521484 298.40753-->
   38835 <!-- 114.99964 296.85861-->
   40802 <!-- 114.48637 296.44791-->
   37280 <!-- 109.99965 294.99997-->
   6593 <!-- 113.46527 294.99997-->
   47930 <!-- 109.99925 290.00009-->
   6593 <!-- 113.46527 294.99997-->
   7414 <!-- 114.07191467285156 294.58316-->
   47930 <!-- 109.99925 290.00009-->
   7414 <!-- 114.07191467285156 294.58316-->
   9483 <!-- 114.99926 290.00009-->
   47930 <!-- 109.99925 290.00009-->
   7414 <!-- 114.07191467285156 294.58316-->
   1149 <!-- 114.99926 294.42514-->
   9483 <!-- 114.99926 290.00009-->
   1149 <!-- 114.99926 294.42514-->
   3736 <!-- 119.99965 292.47379-->
   9198 <!-- 119.99965 290.00009-->
   9198 <!-- 119.99965 290.00009-->
   9483 <!-- 114.99926 290.00009-->
   1149 <!-- 114.99926 294.42514-->
   37389 <!-- 114.23128509521484 298.40753-->
   34913 <!-- 114.99964 298.02838-->
   38835 <!-- 114.99964 296.85861-->
   38835 <!-- 114.99964 296.85861-->
   34913 <!-- 114.99964 298.02838-->
   39024 <!-- 115.44418 297.58572-->
   1260 <!-- 110.68402 284.99997-->
   59343 <!-- 109.99965 285.00018-->
   47930 <!-- 109.99925 290.00009-->
   17138 <!-- 110.977 285.13687-->
   1260 <!-- 110.68402 284.99997-->
   47930 <!-- 109.99925 290.00009-->
   6905 <!-- 109.03598 284.73465-->
   4566 <!-- 108.76801 284.99997-->
   59343 <!-- 109.99965 285.00018-->
   6905 <!-- 109.03598 284.73465-->
   59343 <!-- 109.99965 285.00018-->
   59586 <!-- 109.62309 284.39951-->
   59343 <!-- 109.99965 285.00018-->
   744 <!-- 109.99965 284.57822-->
   59586 <!-- 109.62309 284.39951-->
   1260 <!-- 110.68402 284.99997-->
   744 <!-- 109.99965 284.57822-->
   59343 <!-- 109.99965 285.00018-->
   9483 <!-- 114.99926 290.00009-->
   36616 <!-- 114.99964 284.99997-->
   14844 <!-- 111.33871459960938 285.00018-->
   24442 <!-- 102.28715515136719 288.62317-->
   24413 <!-- 102.12895 288.93622-->
   24162 <!-- 102.98676 289.58423-->
   22893 <!-- 102.69301 288.75729-->
   24442 <!-- 102.28715515136719 288.62317-->
   24162 <!-- 102.98676 289.58423-->
   3272 <!-- 103.43832397460938 288.80209-->
   22893 <!-- 102.69301 288.75729-->
   24162 <!-- 102.98676 289.58423-->
   3272 <!-- 103.43832397460938 288.80209-->
   24162 <!-- 102.98676 289.58423-->
   53488 <!-- 104.99926 290.00027-->
   59792 <!-- 104.45395 289.07037-->
   3272 <!-- 103.43832397460938 288.80209-->
   53488 <!-- 104.99926 290.00027-->
   55704 <!-- 104.99966 289.06998-->
   59792 <!-- 104.45395 289.07037-->
   53488 <!-- 104.99926 290.00027-->
   54865 <!-- 105.46996 289.04788-->
   55704 <!-- 104.99966 289.06998-->
   53488 <!-- 104.99926 290.00027-->
   54865 <!-- 105.46996 289.04788-->
   53488 <!-- 104.99926 290.00027-->
   47930 <!-- 109.99925 290.00009-->
   24162 <!-- 102.98676 289.58423-->
   22063 <!-- 102.28715515136719 290.00009-->
   53488 <!-- 104.99926 290.00027-->
   51624 <!-- 106.23715 288.42215-->
   54865 <!-- 105.46996 289.04788-->
   47930 <!-- 109.99925 290.00009-->
   46180 <!-- 106.82426452636719 287.21548-->
   51624 <!-- 106.23715 288.42215-->
   47930 <!-- 109.99925 290.00009-->
   46180 <!-- 106.82426452636719 287.21548-->
   42874 <!-- 106.30473 287.72934-->
   51624 <!-- 106.23715 288.42215-->
   46180 <!-- 106.82426452636719 287.21548-->
   51147 <!-- 108.3141 285.44974-->
   42414 <!-- 106.48559 286.0307-->
   46180 <!-- 106.82426452636719 287.21548-->
   47930 <!-- 109.99925 290.00009-->
   51147 <!-- 108.3141 285.44974-->
   46180 <!-- 106.82426452636719 287.21548-->
   42414 <!-- 106.48559 286.0307-->
   45584 <!-- 106.25981 286.27667-->
   51624 <!-- 106.23715 288.42215-->
   53216 <!-- 105.74067 288.62317-->
   54865 <!-- 105.46996 289.04788-->
   59343 <!-- 109.99965 285.00018-->
   4566 <!-- 108.76801 284.99997-->
   51147 <!-- 108.3141 285.44974-->
   47930 <!-- 109.99925 290.00009-->
   59343 <!-- 109.99965 285.00018-->
   51147 <!-- 108.3141 285.44974-->
   19020 <!-- 111.65433502197266 284.6228-->
   14844 <!-- 111.33871459960938 285.00018-->
   36616 <!-- 114.99964 284.99997-->
   12344 <!-- 112.46723 283.63943-->
   19020 <!-- 111.65433502197266 284.6228-->
   36616 <!-- 114.99964 284.99997-->
   12344 <!-- 112.46723 283.63943-->
   36616 <!-- 114.99964 284.99997-->
   15973 <!-- 113.16685 281.4494-->
   12344 <!-- 112.46723 283.63943-->
   15836 <!-- 111.92543 283.97479-->
   19020 <!-- 111.65433502197266 284.6228-->
   36616 <!-- 114.99964 284.99997-->
   36375 <!-- 113.84378 280.89053-->
   15973 <!-- 113.16685 281.4494-->
   17295 <!-- 112.80551 281.53897-->
   16263 <!-- 112.55746459960938 281.94098-->
   12344 <!-- 112.46723 283.63943-->
   17295 <!-- 112.80551 281.53897-->
   12344 <!-- 112.46723 283.63943-->
   15973 <!-- 113.16685 281.4494-->
   36375 <!-- 113.84378 280.89053-->
   39422 <!-- 113.32464 281.00241-->
   15973 <!-- 113.16685 281.4494-->
   47876 <!-- 115.00004 280.00009-->
   57353 <!-- 113.97894 280.00009-->
   36375 <!-- 113.84378 280.89053-->
   36616 <!-- 114.99964 284.99997-->
   47876 <!-- 115.00004 280.00009-->
   36375 <!-- 113.84378 280.89053-->
   47693 <!-- 114.45355 279.70636-->
   57353 <!-- 113.97894 280.00009-->
   47876 <!-- 115.00004 280.00009-->
   50269 <!-- 114.49847412109375 278.52179-->
   47693 <!-- 114.45355 279.70636-->
   47876 <!-- 115.00004 280.00009-->
   2051 <!-- 112.99692 274.99979-->
   15838 <!-- 113.39262 275.10257-->
   9749 <!-- 114.99964 275.0-->
   15838 <!-- 113.39262 275.10257-->
   11746 <!-- 114.67934 275.39316-->
   9749 <!-- 114.99964 275.0-->
   15838 <!-- 113.39262 275.10257-->
   19580 <!-- 114.0016 275.4823-->
   11746 <!-- 114.67934 275.39316-->
   11746 <!-- 114.67934 275.39316-->
   57589 <!-- 114.99964 275.68372-->
   9749 <!-- 114.99964 275.0-->
   9749 <!-- 114.99964 275.0-->
   57589 <!-- 114.99964 275.68372-->
   55429 <!-- 115.55942 276.17529-->
   50223 <!-- 118.15746 275.0-->
   9749 <!-- 114.99964 275.0-->
   55429 <!-- 115.55942 276.17529-->
   28395 <!-- 118.25355 276.15735-->
   55429 <!-- 115.55942 276.17529-->
   56161 <!-- 115.33363 276.91269-->
   44631 <!-- 117.93402 275.62-->
   50223 <!-- 118.15746 275.0-->
   55429 <!-- 115.55942 276.17529-->
   28395 <!-- 118.25355 276.15735-->
   44631 <!-- 117.93402 275.62-->
   55429 <!-- 115.55942 276.17529-->
   52890 <!-- 114.56605 277.40448-->
   50843 <!-- 114.25043 277.78439-->
   50269 <!-- 114.49847412109375 278.52179-->
   55385 <!-- 114.99964 277.27032-->
   52890 <!-- 114.56605 277.40448-->
   50269 <!-- 114.49847412109375 278.52179-->
   55385 <!-- 114.99964 277.27032-->
   50269 <!-- 114.49847412109375 278.52179-->
   47876 <!-- 115.00004 280.00009-->
   30433 <!-- 119.99965 280.00009-->
   56161 <!-- 115.33363 276.91269-->
   55385 <!-- 114.99964 277.27032-->
   30433 <!-- 119.99965 280.00009-->
   28395 <!-- 118.25355 276.15735-->
   56161 <!-- 115.33363 276.91269-->
   30433 <!-- 119.99965 280.00009-->
   55385 <!-- 114.99964 277.27032-->
   47876 <!-- 115.00004 280.00009-->
   30433 <!-- 119.99965 280.00009-->
   34650 <!-- 119.99965 276.85272-->
   28395 <!-- 118.25355 276.15735-->
   21161 <!-- 115.79535 271.95383-->
   24591 <!-- 115.73168 271.51135-->
   19301 <!-- 114.99964 271.19177-->
   24205 <!-- 116.43402 272.61743-->
   21161 <!-- 115.79535 271.95383-->
   19301 <!-- 114.99964 271.19177-->
   24205 <!-- 116.43402 272.61743-->
   23182 <!-- 116.40199 272.26984-->
   21161 <!-- 115.79535 271.95383-->
   24205 <!-- 116.43402 272.61743-->
   19301 <!-- 114.99964 271.19177-->
   9749 <!-- 114.99964 275.0-->
   29469 <!-- 117.58285 273.1232-->
   24205 <!-- 116.43402 272.61743-->
   9749 <!-- 114.99964 275.0-->
   29469 <!-- 117.58285 273.1232-->
   9749 <!-- 114.99964 275.0-->
   50223 <!-- 118.15746 275.0-->
   29469 <!-- 117.58285 273.1232-->
   50223 <!-- 118.15746 275.0-->
   21394 <!-- 118.09379 273.31299-->
   29469 <!-- 117.58285 273.1232-->
   30115 <!-- 117.61449432373047 272.74387-->
   24205 <!-- 116.43402 272.61743-->
   9198 <!-- 119.99965 290.00009-->
   3736 <!-- 119.99965 292.47379-->
   5222 <!-- 120.99886 292.27594-->
   30401 <!-- 124.99964 290.00027-->
   9198 <!-- 119.99965 290.00009-->
   5222 <!-- 120.99886 292.27594-->
   29777 <!-- 124.99964 290.28494-->
   30401 <!-- 124.99964 290.00027-->
   5222 <!-- 120.99886 292.27594-->
   29777 <!-- 124.99964 290.28494-->
   22765 <!-- 125.53128 289.99988-->
   30401 <!-- 124.99964 290.00027-->
   9513 <!-- 99.99965 300.00006-->
   1966 <!-- 99.99927 303.30624-->
   12098 <!-- 100.95199584960938 302.26331-->
   9513 <!-- 99.99965 300.00006-->
   12098 <!-- 100.95199584960938 302.26331-->
   16028 <!-- 102.7395 301.18878-->
   9513 <!-- 99.99965 300.00006-->
   16028 <!-- 102.7395 301.18878-->
   16533 <!-- 103.091064453125 300.71475-->
   9513 <!-- 99.99965 300.00006-->
   16533 <!-- 103.091064453125 300.71475-->
   49260 <!-- 104.68677 300.00006-->
   8218 <!-- 99.16411 305.00015-->
   58702 <!-- 97.53049 305.00015-->
   52458 <!-- 98.84536 305.39212-->
   59409 <!-- 111.81406 271.66956-->
   3631 <!-- 112.1164 271.95145-->
   8941 <!-- 112.88398 272.15247-->
   6439 <!-- 112.00351 271.05743-->
   59409 <!-- 111.81406 271.66956-->
   8941 <!-- 112.88398 272.15247-->
   6439 <!-- 112.00351 271.05743-->
   8941 <!-- 112.88398 272.15247-->
   18743 <!-- 114.83715 270.99039-->
   8941 <!-- 112.88398 272.15247-->
   19301 <!-- 114.99964 271.19177-->
   18743 <!-- 114.83715 270.99039-->
   8941 <!-- 112.88398 272.15247-->
   6854 <!-- 113.06444549560547 272.73361-->
   10890 <!-- 113.3177261352539 272.93481-->
   8941 <!-- 112.88398 272.15247-->
   10890 <!-- 113.3177261352539 272.93481-->
   19301 <!-- 114.99964 271.19177-->
   20639 <!-- 114.69027 270.00009-->
   6439 <!-- 112.00351 271.05743-->
   18743 <!-- 114.83715 270.99039-->
   20639 <!-- 114.69027 270.00009-->
   57551 <!-- 111.9582 270.00009-->
   56416 <!-- 111.91366577148438 270.65521-->
   20639 <!-- 114.69027 270.00009-->
   56416 <!-- 111.91366577148438 270.65521-->
   6439 <!-- 112.00351 271.05743-->
   9749 <!-- 114.99964 275.0-->
   19583 <!-- 113.34426 273.78384-->
   59102 <!-- 113.16644 274.3425-->
   9749 <!-- 114.99964 275.0-->
   19301 <!-- 114.99964 271.19177-->
   19583 <!-- 113.34426 273.78384-->
   19301 <!-- 114.99964 271.19177-->
   10890 <!-- 113.3177261352539 272.93481-->
   19583 <!-- 113.34426 273.78384-->
   2241 <!-- 112.62504577636719 274.56601-->
   573 <!-- 112.44457 274.85678-->
   2051 <!-- 112.99692 274.99979-->
   59102 <!-- 113.16644 274.3425-->
   2241 <!-- 112.62504577636719 274.56601-->
   2051 <!-- 112.99692 274.99979-->
   9749 <!-- 114.99964 275.0-->
   59102 <!-- 113.16644 274.3425-->
   2051 <!-- 112.99692 274.99979-->
   49621 <!-- 112.49999 269.7612-->
   57551 <!-- 111.9582 270.00009-->
   20639 <!-- 114.69027 270.00009-->
   20639 <!-- 114.69027 270.00009-->
   29784 <!-- 114.31801 269.64957-->
   49621 <!-- 112.49999 269.7612-->
   9483 <!-- 114.99926 290.00009-->
   4761 <!-- 118.73207 285.48093-->
   36616 <!-- 114.99964 284.99997-->
   9483 <!-- 114.99926 290.00009-->
   14440 <!-- 119.43441 286.30273-->
   4761 <!-- 118.73207 285.48093-->
   9483 <!-- 114.99926 290.00009-->
   10538 <!-- 119.37074 286.83987-->
   14440 <!-- 119.43441 286.30273-->
   9483 <!-- 114.99926 290.00009-->
   9198 <!-- 119.99965 290.00009-->
   10538 <!-- 119.37074 286.83987-->
   36616 <!-- 114.99964 284.99997-->
   55442 <!-- 117.45511 282.13055-->
   47876 <!-- 115.00004 280.00009-->
   36616 <!-- 114.99964 284.99997-->
   52174 <!-- 117.3598 283.33151-->
   55442 <!-- 117.45511 282.13055-->
   36616 <!-- 114.99964 284.99997-->
   48221 <!-- 117.96565 283.93219-->
   52174 <!-- 117.3598 283.33151-->
   36616 <!-- 114.99964 284.99997-->
   21062 <!-- 118.25355 284.50128-->
   48221 <!-- 117.96565 283.93219-->
   36616 <!-- 114.99964 284.99997-->
   50157 <!-- 118.06175 285.00018-->
   21062 <!-- 118.25355 284.50128-->
   4761 <!-- 118.73207 285.48093-->
   50157 <!-- 118.06175 285.00018-->
   36616 <!-- 114.99964 284.99997-->
   55442 <!-- 117.45511 282.13055-->
   18493 <!-- 118.60432434082031 281.59341-->
   47876 <!-- 115.00004 280.00009-->
   18493 <!-- 118.60432434082031 281.59341-->
   30433 <!-- 119.99965 280.00009-->
   47876 <!-- 115.00004 280.00009-->
   18493 <!-- 118.60432434082031 281.59341-->
   22903 <!-- 119.99965 281.30896-->
   30433 <!-- 119.99965 280.00009-->
   9198 <!-- 119.99965 290.00009-->
   12553 <!-- 119.99925 286.99768-->
   10538 <!-- 119.37074 286.83987-->
   58891 <!-- 121.19689 288.23727-->
   12553 <!-- 119.99925 286.99768-->
   9198 <!-- 119.99965 290.00009-->
   58891 <!-- 121.19689 288.23727-->
   9198 <!-- 119.99965 290.00009-->
   1066 <!-- 121.79131 288.28571-->
   9198 <!-- 119.99965 290.00009-->
   30401 <!-- 124.99964 290.00027-->
   1066 <!-- 121.79131 288.28571-->
   30401 <!-- 124.99964 290.00027-->
   59900 <!-- 122.39835 287.81168-->
   1066 <!-- 121.79131 288.28571-->
   30401 <!-- 124.99964 290.00027-->
   27234 <!-- 123.4250259399414 287.25079-->
   59900 <!-- 122.39835 287.81168-->
   30401 <!-- 124.99964 290.00027-->
   31752 <!-- 124.4141 286.93457-->
   27234 <!-- 123.4250259399414 287.25079-->
   59900 <!-- 122.39835 287.81168-->
   56089 <!-- 122.01515 287.90659-->
   1066 <!-- 121.79131 288.28571-->
   27234 <!-- 123.4250259399414 287.25079-->
   3259 <!-- 122.7223 287.28235-->
   59900 <!-- 122.39835 287.81168-->
   31752 <!-- 124.4141 286.93457-->
   28423 <!-- 123.93519 286.93475-->
   27234 <!-- 123.4250259399414 287.25079-->
   30401 <!-- 124.99964 290.00027-->
   33752 <!-- 124.66956 286.58719-->
   31752 <!-- 124.4141 286.93457-->
   30401 <!-- 124.99964 290.00027-->
   32400 <!-- 124.99964 286.58719-->
   33752 <!-- 124.66956 286.58719-->
   32400 <!-- 124.99964 286.58719-->
   30401 <!-- 124.99964 290.00027-->
   23309 <!-- 126.2016 289.49469-->
   30401 <!-- 124.99964 290.00027-->
   22765 <!-- 125.53128 289.99988-->
   23309 <!-- 126.2016 289.49469-->
   22011 <!-- 127.47854614257812 286.46054-->
   32400 <!-- 124.99964 286.58719-->
   23309 <!-- 126.2016 289.49469-->
   35767 <!-- 129.99925 284.99997-->
   22011 <!-- 127.47854614257812 286.46054-->
   23309 <!-- 126.2016 289.49469-->
   35767 <!-- 129.99925 284.99997-->
   23309 <!-- 126.2016 289.49469-->
   27138 <!-- 128.59535 288.19904-->
   30240 <!-- 129.99963 287.53564-->
   35767 <!-- 129.99925 284.99997-->
   27138 <!-- 128.59535 288.19904-->
   23309 <!-- 126.2016 289.49469-->
   18658 <!-- 127.44691 289.21024-->
   27138 <!-- 128.59535 288.19904-->
   18658 <!-- 127.44691 289.21024-->
   29693 <!-- 128.30862 288.73599-->
   27138 <!-- 128.59535 288.19904-->
   23491 <!-- 128.18129 285.73361-->
   21812 <!-- 127.70199 285.79694-->
   22011 <!-- 127.47854614257812 286.46054-->
   35767 <!-- 129.99925 284.99997-->
   23491 <!-- 128.18129 285.73361-->
   22011 <!-- 127.47854614257812 286.46054-->
   35767 <!-- 129.99925 284.99997-->
   37845 <!-- 128.30862 285.00018-->
   23491 <!-- 128.18129 285.73361-->
   30240 <!-- 129.99963 287.53564-->
   11614 <!-- 131.05394 286.61835-->
   35767 <!-- 129.99925 284.99997-->
   17959 <!-- 131.91565 285.57581-->
   44055 <!-- 131.86722 284.99997-->
   35767 <!-- 129.99925 284.99997-->
   11614 <!-- 131.05394 286.61835-->
   10289 <!-- 131.24535 285.82849-->
   35767 <!-- 129.99925 284.99997-->
   10289 <!-- 131.24535 285.82849-->
   17959 <!-- 131.91565 285.57581-->
   35767 <!-- 129.99925 284.99997-->
   23405 <!-- 121.76449 279.99988-->
   30433 <!-- 119.99965 280.00009-->
   22903 <!-- 119.99965 281.30896-->
   34650 <!-- 119.99965 276.85272-->
   30433 <!-- 119.99965 280.00009-->
   18327 <!-- 121.76449 277.95877-->
   30433 <!-- 119.99965 280.00009-->
   23405 <!-- 121.76449 279.99988-->
   18327 <!-- 121.76449 277.95877-->
   16579 <!-- 121.12582 276.85251-->
   34650 <!-- 119.99965 276.85272-->
   18327 <!-- 121.76449 277.95877-->
   16579 <!-- 121.12582 276.85251-->
   18327 <!-- 121.76449 277.95877-->
   25540 <!-- 122.49886 277.57965-->
   16579 <!-- 121.12582 276.85251-->
   25540 <!-- 122.49886 277.57965-->
   14835 <!-- 121.60512 276.6947-->
   25540 <!-- 122.49886 277.57965-->
   22776 <!-- 122.40316 277.13696-->
   14835 <!-- 121.60512 276.6947-->
   38538 <!-- 128.75511 283.93219-->
   41592 <!-- 128.21254 284.15372-->
   35767 <!-- 129.99925 284.99997-->
   41592 <!-- 128.21254 284.15372-->
   37845 <!-- 128.30862 285.00018-->
   35767 <!-- 129.99925 284.99997-->
   38538 <!-- 128.75511 283.93219-->
   35767 <!-- 129.99925 284.99997-->
   34373 <!-- 129.23441 283.45816-->
   35767 <!-- 129.99925 284.99997-->
   31685 <!-- 129.99925 283.14215-->
   34373 <!-- 129.23441 283.45816-->
   48763 <!-- 131.05432 283.23682-->
   31685 <!-- 129.99925 283.14215-->
   35767 <!-- 129.99925 284.99997-->
   51537 <!-- 131.30902 284.56424-->
   48763 <!-- 131.05432 283.23682-->
   35767 <!-- 129.99925 284.99997-->
   43892 <!-- 131.85199 284.81711-->
   51537 <!-- 131.30902 284.56424-->
   35767 <!-- 129.99925 284.99997-->
   44055 <!-- 131.86722 284.99997-->
   43892 <!-- 131.85199 284.81711-->
   35767 <!-- 129.99925 284.99997-->
  </u4_ary>
 </rec>
 <ary type="outlines">
  <rec type="outlines">
   <yes/>
   <v2 x="93.99498" y="269.64957"/>
   <v2 x="131.91565" y="305.39212"/>
   <u4_ary>
    43503 <!-- 96.95344 293.17117-->
    36622 <!-- 98.05891418457031 292.92538-->
    22632 <!-- 98.5788345336914 292.32193-->
    22542 <!-- 98.7438 291.79678-->
    21087 <!-- 99.55591 291.2825-->
    29995 <!-- 99.99965 290.85797-->
    31555 <!-- 100.18793487548828 290.1431-->
    28025 <!-- 101.15864 290.09811-->
    26172 <!-- 101.47426 290.3439-->
    22063 <!-- 102.28715515136719 290.00009-->
    24162 <!-- 102.98676 289.58423-->
    24413 <!-- 102.12895 288.93622-->
    24442 <!-- 102.28715515136719 288.62317-->
    22893 <!-- 102.69301 288.75729-->
    3272 <!-- 103.43832397460938 288.80209-->
    59792 <!-- 104.45395 289.07037-->
    55704 <!-- 104.99966 289.06998-->
    54865 <!-- 105.46996 289.04788-->
    53216 <!-- 105.74067 288.62317-->
    51624 <!-- 106.23715 288.42215-->
    42874 <!-- 106.30473 287.72934-->
    46180 <!-- 106.82426452636719 287.21548-->
    45584 <!-- 106.25981 286.27667-->
    42414 <!-- 106.48559 286.0307-->
    51147 <!-- 108.3141 285.44974-->
    4566 <!-- 108.76801 284.99997-->
    6905 <!-- 109.03598 284.73465-->
    59586 <!-- 109.62309 284.39951-->
    744 <!-- 109.99965 284.57822-->
    1260 <!-- 110.68402 284.99997-->
    17138 <!-- 110.977 285.13687-->
    14844 <!-- 111.33871459960938 285.00018-->
    19020 <!-- 111.65433502197266 284.6228-->
    15836 <!-- 111.92543 283.97479-->
    12344 <!-- 112.46723 283.63943-->
    16263 <!-- 112.55746459960938 281.94098-->
    17295 <!-- 112.80551 281.53897-->
    15973 <!-- 113.16685 281.4494-->
    39422 <!-- 113.32464 281.00241-->
    36375 <!-- 113.84378 280.89053-->
    57353 <!-- 113.97894 280.00009-->
    47693 <!-- 114.45355 279.70636-->
    50269 <!-- 114.49847412109375 278.52179-->
    50843 <!-- 114.25043 277.78439-->
    52890 <!-- 114.56605 277.40448-->
    55385 <!-- 114.99964 277.27032-->
    56161 <!-- 115.33363 276.91269-->
    55429 <!-- 115.55942 276.17529-->
    57589 <!-- 114.99964 275.68372-->
    11746 <!-- 114.67934 275.39316-->
    19580 <!-- 114.0016 275.4823-->
    15838 <!-- 113.39262 275.10257-->
    2051 <!-- 112.99692 274.99979-->
    573 <!-- 112.44457 274.85678-->
    2241 <!-- 112.62504577636719 274.56601-->
    59102 <!-- 113.16644 274.3425-->
    19583 <!-- 113.34426 273.78384-->
    10890 <!-- 113.3177261352539 272.93481-->
    6854 <!-- 113.06444549560547 272.73361-->
    8941 <!-- 112.88398 272.15247-->
    3631 <!-- 112.1164 271.95145-->
    59409 <!-- 111.81406 271.66956-->
    6439 <!-- 112.00351 271.05743-->
    56416 <!-- 111.91366577148438 270.65521-->
    57551 <!-- 111.9582 270.00009-->
    49621 <!-- 112.49999 269.7612-->
    29784 <!-- 114.31801 269.64957-->
    20639 <!-- 114.69027 270.00009-->
    18743 <!-- 114.83715 270.99039-->
    19301 <!-- 114.99964 271.19177-->
    24591 <!-- 115.73168 271.51135-->
    21161 <!-- 115.79535 271.95383-->
    23182 <!-- 116.40199 272.26984-->
    24205 <!-- 116.43402 272.61743-->
    30115 <!-- 117.61449432373047 272.74387-->
    29469 <!-- 117.58285 273.1232-->
    21394 <!-- 118.09379 273.31299-->
    50223 <!-- 118.15746 275.0-->
    44631 <!-- 117.93402 275.62-->
    28395 <!-- 118.25355 276.15735-->
    34650 <!-- 119.99965 276.85272-->
    16579 <!-- 121.12582 276.85251-->
    14835 <!-- 121.60512 276.6947-->
    22776 <!-- 122.40316 277.13696-->
    25540 <!-- 122.49886 277.57965-->
    18327 <!-- 121.76449 277.95877-->
    23405 <!-- 121.76449 279.99988-->
    22903 <!-- 119.99965 281.30896-->
    18493 <!-- 118.60432434082031 281.59341-->
    55442 <!-- 117.45511 282.13055-->
    52174 <!-- 117.3598 283.33151-->
    48221 <!-- 117.96565 283.93219-->
    21062 <!-- 118.25355 284.50128-->
    50157 <!-- 118.06175 285.00018-->
    4761 <!-- 118.73207 285.48093-->
    14440 <!-- 119.43441 286.30273-->
    10538 <!-- 119.37074 286.83987-->
    12553 <!-- 119.99925 286.99768-->
    58891 <!-- 121.19689 288.23727-->
    1066 <!-- 121.79131 288.28571-->
    56089 <!-- 122.01515 287.90659-->
    59900 <!-- 122.39835 287.81168-->
    3259 <!-- 122.7223 287.28235-->
    27234 <!-- 123.4250259399414 287.25079-->
    28423 <!-- 123.93519 286.93475-->
    31752 <!-- 124.4141 286.93457-->
    33752 <!-- 124.66956 286.58719-->
    32400 <!-- 124.99964 286.58719-->
    22011 <!-- 127.47854614257812 286.46054-->
    21812 <!-- 127.70199 285.79694-->
    23491 <!-- 128.18129 285.73361-->
    37845 <!-- 128.30862 285.00018-->
    41592 <!-- 128.21254 284.15372-->
    38538 <!-- 128.75511 283.93219-->
    34373 <!-- 129.23441 283.45816-->
    31685 <!-- 129.99925 283.14215-->
    48763 <!-- 131.05432 283.23682-->
    51537 <!-- 131.30902 284.56424-->
    43892 <!-- 131.85199 284.81711-->
    44055 <!-- 131.86722 284.99997-->
    17959 <!-- 131.91565 285.57581-->
    10289 <!-- 131.24535 285.82849-->
    11614 <!-- 131.05394 286.61835-->
    30240 <!-- 129.99963 287.53564-->
    27138 <!-- 128.59535 288.19904-->
    29693 <!-- 128.30862 288.73599-->
    18658 <!-- 127.44691 289.21024-->
    23309 <!-- 126.2016 289.49469-->
    22765 <!-- 125.53128 289.99988-->
    29777 <!-- 124.99964 290.28494-->
    5222 <!-- 120.99886 292.27594-->
    3736 <!-- 119.99965 292.47379-->
    1149 <!-- 114.99926 294.42514-->
    7414 <!-- 114.07191467285156 294.58316-->
    6593 <!-- 113.46527 294.99997-->
    49565 <!-- 113.08246 295.59433-->
    33513 <!-- 113.33754 295.879-->
    40802 <!-- 114.48637 296.44791-->
    38835 <!-- 114.99964 296.85861-->
    39024 <!-- 115.44418 297.58572-->
    34913 <!-- 114.99964 298.02838-->
    37389 <!-- 114.23128509521484 298.40753-->
    57126 <!-- 109.99925 297.83844-->
    59964 <!-- 109.25159454345703 298.12289-->
    36809 <!-- 107.78325 298.12329-->
    48749 <!-- 104.99966 299.54517-->
    49260 <!-- 104.68677 300.00006-->
    16533 <!-- 103.091064453125 300.71475-->
    16028 <!-- 102.7395 301.18878-->
    12098 <!-- 100.95199584960938 302.26331-->
    1966 <!-- 99.99927 303.30624-->
    9101 <!-- 99.3559 304.15961-->
    8218 <!-- 99.16411 305.00015-->
    52458 <!-- 98.84536 305.39212-->
    58702 <!-- 97.53049 305.00015-->
    6698 <!-- 96.71462 304.27603-->
    49142 <!-- 95.62676 303.86807-->
    49917 <!-- 94.99982 302.82315-->
    50677 <!-- 93.99498 301.14841-->
    727 <!-- 95.00004577636719 300.00006-->
    54393 <!-- 96.57865 299.1087-->
    54355 <!-- 97.74989 296.55255-->
    38280 <!-- 97.34943 295.00012-->
    41209 <!-- 97.48994 293.89914-->
   </u4_ary>
   <ary type="connectivity">
    <connectivity region="48 (mediterranean_sea)" area="0" from="0" to="57"/>
    <connectivity region="48 (mediterranean_sea)" area="3" from="58" to="63"/>
    <connectivity region="48 (mediterranean_sea)" area="0" from="64" to="115"/>
    <connectivity region="64 (adriatic_sea)" area="0" from="116" to="152"/>
    <connectivity region="63 (the_papal_states)" area="0" from="153" to="163"/>
   </ary>
  </rec>
 </ary>
 <u2>53</u2><!-- Impassable Land Areas ID (65535=Passable) -->
 <u2>35</u2><!-- Island ID (65535=Navigable, 104=ETW Mainland) -->
</rec>
