<?xml version="1.0"?>
<rec type="OBSTACLE_BASE_GRID_NODE">
 <u>33921</u>
 <u>3</u>
 <ary type="MANAGED_OBSTACLE_BOUNDARY">
  <rec type="MANAGED_OBSTACLE_BOUNDARY">
   <u>1395</u>
   <u>0</u>
   <yes/>
   <u4_ary>44 1</u4_ary>
  </rec>
  <rec type="MANAGED_OBSTACLE_BOUNDARY">
   <u>2399</u>
   <u>1</u>
   <yes/>
   <u4_ary>68 1</u4_ary>
  </rec>
  <rec type="MANAGED_OBSTACLE_BOUNDARY">
   <u>2561</u>
   <u>2</u>
   <yes/>
   <u4_ary>4 1 8 1 44 1 48 1 68 1</u4_ary>
  </rec>
  <rec type="MANAGED_OBSTACLE_BOUNDARY">
   <u>1582</u>
   <u>1</u>
   <yes/>
   <u4_ary>48 1</u4_ary>
  </rec>
  <rec type="MANAGED_OBSTACLE_BOUNDARY">
   <u>278</u>
   <u>0</u>
   <yes/>
   <u4_ary>4 1 8 1</u4_ary>
  </rec>
  <rec type="MANAGED_OBSTACLE_BOUNDARY">
   <u>219</u>
   <u>0</u>
   <yes/>
   <u4_ary>8 1</u4_ary>
  </rec>
  <rec type="MANAGED_OBSTACLE_BOUNDARY">
   <u>1491</u>
   <u>0</u>
   <yes/>
   <u4_ary>4 1 8 1 44 1</u4_ary>
  </rec>
  <rec type="MANAGED_OBSTACLE_BOUNDARY">
   <u>1689</u>
   <u>1</u>
   <yes/>
   <u4_ary>4 1 8 1 44 1 48 1</u4_ary>
  </rec>
  <rec type="MANAGED_OBSTACLE_BOUNDARY">
   <u>3135</u>
   <u>0</u>
   <yes/>
   <u4_ary>84 1</u4_ary>
  </rec>
  <rec type="MANAGED_OBSTACLE_BOUNDARY">
   <u>134</u>
   <u>0</u>
   <yes/>
   <u4_ary>4 1</u4_ary>
  </rec>
  <rec type="MANAGED_OBSTACLE_BOUNDARY">
   <u>3291</u>
   <u>2</u>
   <yes/>
   <u4_ary>4 1 8 1 44 1 48 1 68 1 84 1</u4_ary>
  </rec>
 </ary>
 <ary type="MANAGED_OBSTACLE_BOUNDARY">
  <rec type="MANAGED_OBSTACLE_BOUNDARY">
   <yes/>
   <u4_ary>84 1</u4_ary>
  </rec>
  <rec type="MANAGED_OBSTACLE_BOUNDARY">
   <yes/>
   <u4_ary>68 1</u4_ary>
  </rec>
  <rec type="MANAGED_OBSTACLE_BOUNDARY">
   <yes/>
   <u4_ary>48 1</u4_ary>
  </rec>
  <rec type="MANAGED_OBSTACLE_BOUNDARY">
   <yes/>
   <u4_ary>44 1</u4_ary>
  </rec>
  <rec type="MANAGED_OBSTACLE_BOUNDARY">
   <yes/>
   <u4_ary>8 1</u4_ary>
  </rec>
  <rec type="MANAGED_OBSTACLE_BOUNDARY">
   <yes/>
   <u4_ary>4 1</u4_ary>
  </rec>
  <rec type="MANAGED_OBSTACLE_BOUNDARY">
   <yes/>
   <u4_ary>4 1 8 1</u4_ary>
  </rec>
  <rec type="MANAGED_OBSTACLE_BOUNDARY">
   <yes/>
   <u4_ary>4 1 8 1 44 1</u4_ary>
  </rec>
  <rec type="MANAGED_OBSTACLE_BOUNDARY">
   <yes/>
   <u4_ary>4 1 8 1 44 1 48 1</u4_ary>
  </rec>
  <rec type="MANAGED_OBSTACLE_BOUNDARY">
   <yes/>
   <u4_ary>4 1 8 1 44 1 48 1 68 1</u4_ary>
  </rec>
  <rec type="MANAGED_OBSTACLE_BOUNDARY">
   <yes/>
   <u4_ary>4 1 8 1 44 1 48 1 68 1 84 1</u4_ary>
  </rec>
 </ary>
</rec>
