<?xml version="1.0"?>
<rec type="OBSTACLE_BASE_GRID_NODE">
 <u>33354</u>
 <u>1</u>
 <ary type="MANAGED_OBSTACLE_BOUNDARY">
  <rec type="MANAGED_OBSTACLE_BOUNDARY">
   <u>19564</u>
   <u>0</u>
   <yes/>
   <u4_ary>573160218 0</u4_ary>
  </rec>
  <rec type="MANAGED_OBSTACLE_BOUNDARY">
   <u>26807</u>
   <u>1</u>
   <yes/>
   <u4_ary>52 1 608945321 1 573160218 1 562042818 0</u4_ary>
  </rec>
  <rec type="MANAGED_OBSTACLE_BOUNDARY">
   <u>19418</u>
   <u>0</u>
   <yes/>
   <u4_ary>52 1 573160218 1</u4_ary>
  </rec>
  <rec type="MANAGED_OBSTACLE_BOUNDARY">
   <u>19682</u>
   <u>0</u>
   <yes/>
   <u4_ary>566919178 0</u4_ary>
  </rec>
  <rec type="MANAGED_OBSTACLE_BOUNDARY">
   <u>8174</u>
   <u>0</u>
   <yes/>
   <u4_ary>52 1</u4_ary>
  </rec>
  <rec type="MANAGED_OBSTACLE_BOUNDARY">
   <u>27627</u>
   <u>0</u>
   <yes/>
   <u4_ary>52 1 608945321 1 573160218 3</u4_ary>
  </rec>
  <rec type="MANAGED_OBSTACLE_BOUNDARY">
   <u>19317</u>
   <u>0</u>
   <yes/>
   <u4_ary>52 1 608945321 1</u4_ary>
  </rec>
  <rec type="MANAGED_OBSTACLE_BOUNDARY">
   <u>26697</u>
   <u>1</u>
   <yes/>
   <u4_ary>562042818 0</u4_ary>
  </rec>
  <rec type="MANAGED_OBSTACLE_BOUNDARY">
   <u>19281</u>
   <u>0</u>
   <yes/>
   <u4_ary>608945321 1</u4_ary>
  </rec>
  <rec type="MANAGED_OBSTACLE_BOUNDARY">
   <u>19717</u>
   <u>0</u>
   <yes/>
   <u4_ary>52 1 608945321 1 573160218 0 566919178 0</u4_ary>
  </rec>
  <rec type="MANAGED_OBSTACLE_BOUNDARY">
   <u>19907</u>
   <u>0</u>
   <yes/>
   <u4_ary>52 1 608945321 1 573160218 1</u4_ary>
  </rec>
  <rec type="MANAGED_OBSTACLE_BOUNDARY">
   <u>27579</u>
   <u>0</u>
   <yes/>
   <u4_ary>573160218 3</u4_ary>
  </rec>
  <rec type="MANAGED_OBSTACLE_BOUNDARY">
   <u>19716</u>
   <u>0</u>
   <yes/>
   <u4_ary>52 1 608945321 1 573160218 0</u4_ary>
  </rec>
  <rec type="MANAGED_OBSTACLE_BOUNDARY">
   <u>19382</u>
   <u>0</u>
   <yes/>
   <u4_ary>573160218 1</u4_ary>
  </rec>
 </ary>
 <ary type="MANAGED_OBSTACLE_BOUNDARY">
  <rec type="MANAGED_OBSTACLE_BOUNDARY">
   <yes/>
   <u4_ary>573160218 3</u4_ary>
  </rec>
  <rec type="MANAGED_OBSTACLE_BOUNDARY">
   <yes/>
   <u4_ary>562042818 0</u4_ary>
  </rec>
  <rec type="MANAGED_OBSTACLE_BOUNDARY">
   <yes/>
   <u4_ary>566919178 0</u4_ary>
  </rec>
  <rec type="MANAGED_OBSTACLE_BOUNDARY">
   <yes/>
   <u4_ary>573160218 0</u4_ary>
  </rec>
  <rec type="MANAGED_OBSTACLE_BOUNDARY">
   <yes/>
   <u4_ary>573160218 1</u4_ary>
  </rec>
  <rec type="MANAGED_OBSTACLE_BOUNDARY">
   <yes/>
   <u4_ary>608945321 1</u4_ary>
  </rec>
  <rec type="MANAGED_OBSTACLE_BOUNDARY">
   <yes/>
   <u4_ary>52 1</u4_ary>
  </rec>
  <rec type="MANAGED_OBSTACLE_BOUNDARY">
   <yes/>
   <u4_ary>52 1 608945321 1</u4_ary>
  </rec>
  <rec type="MANAGED_OBSTACLE_BOUNDARY">
   <yes/>
   <u4_ary>52 1 573160218 1</u4_ary>
  </rec>
  <rec type="MANAGED_OBSTACLE_BOUNDARY">
   <yes/>
   <u4_ary>52 1 608945321 1 573160218 0</u4_ary>
  </rec>
  <rec type="MANAGED_OBSTACLE_BOUNDARY">
   <yes/>
   <u4_ary>52 1 608945321 1 573160218 0 566919178 0</u4_ary>
  </rec>
  <rec type="MANAGED_OBSTACLE_BOUNDARY">
   <yes/>
   <u4_ary>52 1 608945321 1 573160218 1</u4_ary>
  </rec>
  <rec type="MANAGED_OBSTACLE_BOUNDARY">
   <yes/>
   <u4_ary>52 1 608945321 1 573160218 1 562042818 0</u4_ary>
  </rec>
  <rec type="MANAGED_OBSTACLE_BOUNDARY">
   <yes/>
   <u4_ary>52 1 608945321 1 573160218 3</u4_ary>
  </rec>
 </ary>
</rec>
