<?xml version="1.0"?>
<rec type="OBSTACLE_BASE_GRID_NODE">
 <u>40144</u>
 <u>2</u>
 <ary type="MANAGED_OBSTACLE_BOUNDARY">
  <rec type="MANAGED_OBSTACLE_BOUNDARY">
   <u>20567</u>
   <u>0</u>
   <yes/>
   <u4_ary>76 1 563511306 0</u4_ary>
  </rec>
  <rec type="MANAGED_OBSTACLE_BOUNDARY">
   <u>26502</u>
   <u>0</u>
   <yes/>
   <u4_ary>76 1 563511306 1 570791026 0</u4_ary>
  </rec>
  <rec type="MANAGED_OBSTACLE_BOUNDARY">
   <u>28144</u>
   <u>0</u>
   <yes/>
   <u4_ary>76 1 563511306 3</u4_ary>
  </rec>
  <rec type="MANAGED_OBSTACLE_BOUNDARY">
   <u>28080</u>
   <u>0</u>
   <yes/>
   <u4_ary>563511306 3</u4_ary>
  </rec>
  <rec type="MANAGED_OBSTACLE_BOUNDARY">
   <u>27721</u>
   <u>0</u>
   <yes/>
   <u4_ary>76 1 570791026 0</u4_ary>
  </rec>
  <rec type="MANAGED_OBSTACLE_BOUNDARY">
   <u>28665</u>
   <u>0</u>
   <yes/>
   <u4_ary>570791026 1</u4_ary>
  </rec>
  <rec type="MANAGED_OBSTACLE_BOUNDARY">
   <u>20479</u>
   <u>0</u>
   <yes/>
   <u4_ary>563511306 0</u4_ary>
  </rec>
  <rec type="MANAGED_OBSTACLE_BOUNDARY">
   <u>22464</u>
   <u>0</u>
   <yes/>
   <u4_ary>563511306 1</u4_ary>
  </rec>
  <rec type="MANAGED_OBSTACLE_BOUNDARY">
   <u>23293</u>
   <u>0</u>
   <yes/>
   <u4_ary>570791026 0</u4_ary>
  </rec>
  <rec type="MANAGED_OBSTACLE_BOUNDARY">
   <u>22628</u>
   <u>0</u>
   <yes/>
   <u4_ary>76 1 563511306 1</u4_ary>
  </rec>
  <rec type="MANAGED_OBSTACLE_BOUNDARY">
   <u>23400</u>
   <u>0</u>
   <yes/>
   <u4_ary>76 1 563511306 0 570791026 0</u4_ary>
  </rec>
  <rec type="MANAGED_OBSTACLE_BOUNDARY">
   <u>29252</u>
   <u>0</u>
   <yes/>
   <u4_ary>76 1 563511306 0 570791026 1</u4_ary>
  </rec>
  <rec type="MANAGED_OBSTACLE_BOUNDARY">
   <u>13558</u>
   <u>0</u>
   <yes/>
   <u4_ary>76 1</u4_ary>
  </rec>
  <rec type="MANAGED_OBSTACLE_BOUNDARY">
   <u>28145</u>
   <u>0</u>
   <yes/>
   <u4_ary>76 1 563511306 3 570791026 0</u4_ary>
  </rec>
 </ary>
 <ary type="MANAGED_OBSTACLE_BOUNDARY">
  <rec type="MANAGED_OBSTACLE_BOUNDARY">
   <yes/>
   <u4_ary>570791026 1</u4_ary>
  </rec>
  <rec type="MANAGED_OBSTACLE_BOUNDARY">
   <yes/>
   <u4_ary>563511306 3</u4_ary>
  </rec>
  <rec type="MANAGED_OBSTACLE_BOUNDARY">
   <yes/>
   <u4_ary>570791026 0</u4_ary>
  </rec>
  <rec type="MANAGED_OBSTACLE_BOUNDARY">
   <yes/>
   <u4_ary>563511306 1</u4_ary>
  </rec>
  <rec type="MANAGED_OBSTACLE_BOUNDARY">
   <yes/>
   <u4_ary>563511306 0</u4_ary>
  </rec>
  <rec type="MANAGED_OBSTACLE_BOUNDARY">
   <yes/>
   <u4_ary>76 1</u4_ary>
  </rec>
  <rec type="MANAGED_OBSTACLE_BOUNDARY">
   <yes/>
   <u4_ary>76 1 563511306 0</u4_ary>
  </rec>
  <rec type="MANAGED_OBSTACLE_BOUNDARY">
   <yes/>
   <u4_ary>76 1 563511306 1</u4_ary>
  </rec>
  <rec type="MANAGED_OBSTACLE_BOUNDARY">
   <yes/>
   <u4_ary>76 1 563511306 0 570791026 0</u4_ary>
  </rec>
  <rec type="MANAGED_OBSTACLE_BOUNDARY">
   <yes/>
   <u4_ary>76 1 563511306 1 570791026 0</u4_ary>
  </rec>
  <rec type="MANAGED_OBSTACLE_BOUNDARY">
   <yes/>
   <u4_ary>76 1 570791026 0</u4_ary>
  </rec>
  <rec type="MANAGED_OBSTACLE_BOUNDARY">
   <yes/>
   <u4_ary>76 1 563511306 3</u4_ary>
  </rec>
  <rec type="MANAGED_OBSTACLE_BOUNDARY">
   <yes/>
   <u4_ary>76 1 563511306 3 570791026 0</u4_ary>
  </rec>
  <rec type="MANAGED_OBSTACLE_BOUNDARY">
   <yes/>
   <u4_ary>76 1 563511306 0 570791026 1</u4_ary>
  </rec>
 </ary>
</rec>
